Workbook

Sheet Raw_Financials
B1: 2015 | C1: 2016 | D1: 2017 | E1: 2018 | F1: 2019 | G1: 2020 | H1: 2021 | I1: 2022 | J1: 2023 | K1: 2024
A2: Periods | B2: 12 | C2: 12 | D2: 12 | E2: 12 | F2: 12 | G2: 12 | H2: 12 | I2: 12 | J2: 12 | K2: 12
A3: Total Non-Current Assets | B3: =B22+B32+SUM(B33:B38)+SUM(B40:B46)-B39 -> 948303.32 | C3: =C22+C32+SUM(C33:C38)+SUM(C40:C46)-C39 -> 1132571.1 | D3: =D22+D32+SUM(D33:D38)+SUM(D40:D46)-D39 -> 1321849.3 | E3: =E22+E32+SUM(E33:E38)+SUM(E40:E46)-E39 -> 1666215.1 | F3: =F22+F32+SUM(F33:F38)+SUM(F40:F46)-F39 -> 2243152.9 | G3: =G22+G32+SUM(G33:G38)+SUM(G40:G46)-G39 -> 2519903.1 | H3: =H22+H32+SUM(H33:H38)+SUM(H40:H46)-H39 -> 3184128 | I3: =I22+I32+SUM(I33:I38)+SUM(I40:I46)-I39 -> 10090610 | ... K3: =K22+K32+SUM(K33:K38)+SUM(K40:K46)-K39 -> 24234704
A4: Total Current Assets | B4: =B56+B71+SUM(B57:B68)+SUM(B72:B75) -> 165868.98 | C4: =C56+C71+SUM(C57:C68)+SUM(C72:C75) -> 174481.95 | D4: =D56+D71+SUM(D57:D68)+SUM(D72:D75) -> 188553.52 | E4: =E56+E71+SUM(E57:E68)+SUM(E72:E75) -> 226511.52 | F4: =F56+F71+SUM(F57:F68)+SUM(F72:F75) -> 237941.1 | G4: =G56+G71+SUM(G57:G68)+SUM(G72:G75) -> 438016.49 | H4: =H56+H71+SUM(H57:H68)+SUM(H72:H75) -> 443279.05 | I4: =I56+I71+SUM(I57:I68)+SUM(I72:I75) -> 2104055.3 | ... K4: =K56+K71+SUM(K57:K68)+SUM(K72:K75) -> 6510695
A5: Total Equity & Reserves | B5: =+B82+B93+B94 -> -18816.879 | C5: =+C82+C93+C94 -> -6374.964 | D5: =+D82+D93+D94 -> -11517.088 | E5: =+E82+E93+E94 -> -13802.036 | F5: =+F82+F93+F94 -> 41655.046 | G5: =+G82+G93+G94 -> 16267.905 | H5: =+H82+H93+H94 -> 12877.404 | I5: =+I82+I93+I94 -> 5810755.9 | ... K5: =+K82+K93+K94 -> 17097795
A6: Total Non-Current Liabilities | B6: =+B100+B108+B111+B122 -> 949085.87 | C6: =+C100+C108+C111+C122 -> 1047559.2 | D6: =+D100+D108+D111+D122 -> 1145402.9 | E6: =+E100+E108+E111+E122 -> 1379534.1 | F6: =+F100+F108+F111+F122 -> 1935837.4 | G6: =+G100+G108+G111+G122 -> 2250777.5 | H6: =+H100+H108+H111+H122 -> 2512094.9 | I6: =+I100+I108+I111+I122 -> 3259756.4 | ... K6: =+K100+K108+K111+K122 -> 11149770
A7: Total Current Liabilities | B7: =+B135+B138+B140+B158 -> 177777.95 | C7: =+C135+C138+C140+C158 -> 265868.83 | D7: =+D135+D138+D140+D158 -> 376517.02 | E7: =+E135+E138+E140+E158 -> 526994.59 | F7: =+F135+F138+F140+F158 -> 503601.55 | G7: =+G135+G138+G140+G158 -> 690874.17 | H7: =+H135+H138+H140+H158 -> 1102434.7 | I7: =+I135+I138+I140+I158 -> 3124153 | ... K7: =+K135+K138+K140+K158 -> 2497833.1
A8: Total Income & Expenses | B8: =+B222+SUM(B223:B225) -> 284286.33 | C8: =+C222+SUM(C223:C225) -> -72133.792 | D8: =+D222+SUM(D223:D225) -> -7653.73 | E8: =+E222+SUM(E223:E225) -> -2785.898 | F8: =+F222+SUM(F223:F225) -> 15228.112 | G8: =+G222+SUM(G223:G225) -> -150451.34 | H8: =+H222+SUM(H223:H225) -> -16279.273 | I8: =+I222+SUM(I223:I225) -> 167380.9 | ... K8: =+K222+SUM(K223:K225) -> 1111728.1
A9: Total Assets | B9: =+B3+B4 -> 1114172.3 | C9: =+C3+C4 -> 1307053 | D9: =+D3+D4 -> 1510402.8 | E9: =+E3+E4 -> 1892726.6 | F9: =+F3+F4 -> 2481094 | G9: =+G3+G4 -> 2957919.6 | H9: =+H3+H4 -> 3627407 | I9: =+I3+I4 -> 12194665 | ... K9: =+K3+K4 -> 30745399
A10: Total Liabs & Net Worth | B10: =+B5+B6+B7 -> 1108046.9 | C10: =+C5+C6+C7 -> 1307053 | D10: =+D5+D6+D7 -> 1510402.8 | E10: =+E5+E6+E7 -> 1892726.6 | F10: =+F5+F6+F7 -> 2481094 | G10: =+G5+G6+G7 -> 2957919.6 | H10: =+H5+H6+H7 -> 3627407 | I10: =+I5+I6+I7 -> 12194665 | ... K10: =+K5+K6+K7 -> 30745399
A11: Land | B11: 14032.667 | C11: 14032.667 | D11: 23403.323 | E11: 33060.353 | F11: 103852.85 | G11: 101279.09 | H11: 98968.693 | I11: 120278.06 | J11: 290929.45 | K11: 448557.67
A12: Buildings | B12: 833762.12 | C12: 1043360.1 | D12: 1260884.4 | E12: 1617813.9 | F12: 1804326.9 | G12: 2078253.5 | H12: 2557937 | I12: 7193567.1 | J12: 13525188 | K12: 16975662
A13: Leasehold Improvements | B13: 1403.519 | C13: 1427.037 | D13: 2041.371 | E13: 2721.856 | F13: 3448.04 | G13: 3453.29 | H13: 3511.326 | I13: 19925.234 | J13: 25704.472 | K13: 28709.24
A14: Plant & Equipment | B14: 20939.671 | C14: 25333.043 | D14: 29666.922 | E14: 34707.234 | F14: 36676.018 | G14: 41352.778 | H14: 49195.082 | I14: 215053.46 | J14: 368293.23 | K14: 432329.51
A15: Furniture & Fixtures | B15: 119819.36 | C15: 153420.68 | D15: 181671.88 | E15: 206840.7 | F15: 240029.24 | G15: 259654.77 | H15: 304228.85 | I15: 1555545.8 | J15: 2211598.6 | K15: 2915529
A16: Vehicles & Transport Equipment | B16: 78074.387 | C16: 78665.806 | D16: 111033.76 | E16: 140028.73 | F16: 158375.26 | G16: 194663.89 | H16: 208611.15 | I16: 905914.41 | J16: 1260059.8 | K16: 952913.3
A17: Other Fixed Assets | B17: 0 | C17: 0 | D17: 0 | E17: 0 | F17: 0 | G17: 0 | H17: 0 | I17: 14708.053 | J17: 35116.507 | K17: 156914.68
A18: Construction in Progress | B18: 14039.53 | C18: 2262.903 | D18: 1688.715 | E18: 766.351 | F18: 1314.864 | G18: 5537.918 | H18: 69886.989 | I18: 3029387 | J18: 3600896.8 | K18: 7964508.4
A19: Property Development Investments | B19: 0 | C19: 0 | D19: 0 | E19: 0 | F19: 0 | G19: 0 | H19: 0 | I19: 0 | J19: 0 | K19: 0
A20: Gross Fixed Assets | B20: =SUM(B11:B19) -> 1082071.3 | C20: =SUM(C11:C19) -> 1318502.2 | D20: =SUM(D11:D19) -> 1610390.4 | E20: =SUM(E11:E19) -> 2035939.1 | F20: =SUM(F11:F19) -> 2348023.1 | G20: =SUM(G11:G19) -> 2684195.2 | H20: =SUM(H11:H19) -> 3292339 | I20: =SUM(I11:I19) -> 13054379 | ... K20: =SUM(K11:K19) -> 29875124
A21: Accum Deprec & Impairment (-) | B21: 171723.6 | C21: 232985.01 | D21: 312488.9 | E21: 411010.59 | F21: 509449.8 | G21: 618698.62 | H21: 747092.1 | I21: 3843932.8 | J21: 5434710.7 | K21: 7103298
A22: Net Fixed Assets | B22: =+B20-B21 -> 910347.65 | C22: =+C20-C21 -> 1085517.2 | D22: =+D20-D21 -> 1297901.5 | E22: =+E20-E21 -> 1624928.5 | F22: =+F20-F21 -> 1838573.3 | G22: =+G20-G21 -> 2065496.6 | H22: =+H20-H21 -> 2545246.9 | I22: =+I20-I21 -> 9210446.3 | ... K22: =+K20-K21 -> 22771826
A23: Goodwill | B23: 5018.69 | C23: 5018.69 | D23: 5018.689 | E23: 5018.689 | F23: 5018.689 | G23: 5018.689 | H23: 45902.294 | I23: 5018.689 | J23: 5018.689 | K23: 5018.689
A24: Goodwill impairment(-) | B24: 0 | C24: 0 | D24: 0 | E24: 0 | F24: 0 | G24: 0 | H24: 0 | I24: 0 | J24: 0 | K24: 0
A25: Concessions, Licenses & Trdmrks | B25: 0 | C25: 0 | D25: 0 | E25: 0 | F25: 0 | G25: 0 | H25: 0 | I25: 0 | J25: 0 | K25: 0
A26: Patents | B26: 0 | C26: 0 | D26: 0 | E26: 0 | F26: 0 | G26: 0 | H26: 0 | I26: 0 | J26: 0 | K26: 0
A27: Start-Up Capitalized Expenses | B27: 0 | C27: 0 | D27: 0 | E27: 0 | F27: 0 | G27: 0 | H27: 0 | I27: 0 | J27: 0 | K27: 0
A28: R&D Capitalized Expenses | B28: 0 | C28: 0 | D28: 0 | E28: 0 | F28: 0 | G28: 0 | H28: 0 | I28: 0 | J28: 0 | K28: 0
A29: Leasings | B29: 0 | C29: 0 | D29: 0 | E29: 0 | F29: 0 | G29: 0 | H29: 0 | I29: 0 | J29: 0 | K29: 0
A30: Other Intangible Assets | B30: 1171.631 | C30: 13580.647 | D30: 14037.345 | E30: 39713.438 | F30: 40539.995 | G30: 41274.217 | H30: 46182.106 | I30: 531466.26 | J30: 758034.45 | K30: 1025764.9
A31: Accum Intgbl Assets Amort(-) | B31: 0 | C31: 8777.925 | D31: 11429.745 | E31: 18887.544 | F31: 26246.241 | G31: 32292.361 | H31: 39465.957 | I31: 370735.58 | J31: 586587.06 | K31: 793925.07
A32: Net Intangibles | B32: =+B23-B24+SUM(B25:B30)-B31 -> 6190.321 | C32: =+C23-C24+SUM(C25:C30)-C31 -> 9821.412 | D32: =+D23-D24+SUM(D25:D30)-D31 -> 7626.289 | E32: =+E23-E24+SUM(E25:E30)-E31 -> 25844.583 | F32: =+F23-F24+SUM(F25:F30)-F31 -> 19312.443 | G32: =+G23-G24+SUM(G25:G30)-G31 -> 14000.545 | H32: =+H23-H24+SUM(H25:H30)-H31 -> 52618.443 | I32: =+I23-I24+SUM(I25:I30)-I31 -> 165749.36 | ... K32: =+K23-K24+SUM(K25:K30)-K31 -> 236858.56
A33: Investments in Group Companies and LT Associates | B33: 744.224 | C33: 979.224 | D33: 9934.645 | E33: 11068.502 | F33: 17929.224 | G33: 15245.519 | H33: 41104.146 | I33: 75974.125 | J33: 310568.03 | K33: 557041.8
A34: Investments in Associates | B34: 499.623 | C34: 11206.319 | D34: 0 | E34: 0 | F34: 0 | G34: 0 | H34: 0 | I34: 0 | J34: 0 | K34: 0
A35: Invest in JVs & Partnerships | B35: 0 | C35: 0 | D35: 0 | E35: 0 | F35: 0 | G35: 0 | H35: 0 | I35: 0 | J35: 0 | K35: 0
A36: Due from Related Parties(LTP) | B36: 13057.348 | C36: 1874.545 | D36: 0 | E36: 0 | F36: 0 | G36: 0 | H36: 0 | I36: 0 | J36: 0 | K36: 0
A37: Due from S'holder(LTP) | B37: 3939.969 | C37: 14655.045 | D37: 0 | E37: 0 | F37: 0 | G37: 0 | H37: 0 | I37: 47724.664 | J37: 0 | K37: 0
A38: Secur & Other Fincl Assets(LTP) | B38: 0 | C38: 0 | D38: 0 | E38: 0 | F38: 0 | G38: 0 | H38: 0 | I38: 0 | J38: 0 | K38: 0
A39: Accum Deprec of Financial Assets(-) | B39: 0 | C39: 0 | D39: 0 | E39: 0 | F39: 0 | G39: 0 | H39: 0 | I39: 0 | J39: 0 | K39: 0
A40: Deriv & Hedg Assets(LTP) | B40: 0 | C40: 0 | D40: 0 | E40: 0 | F40: 0 | G40: 0 | H40: 0 | I40: 0 | J40: 0 | K40: 0
A41: Rtrmnt Plan Actuarial Surplus | B41: 0 | C41: 0 | D41: 0 | E41: 0 | F41: 0 | G41: 0 | H41: 0 | I41: 0 | J41: 0 | K41: 0
A42: Other Non-Current Assets | B42: 0 | C42: 0.002 | D42: 0 | E42: 0 | F42: 93.824 | G42: 0 | H42: 0.97 | I42: 0 | J42: 0 | K42: 0
A43: Deferred Tax Assets | B43: 0 | C43: 0 | D43: 0 | E43: 0 | F43: 0 | G43: 0 | H43: 0 | I43: 0 | J43: 0 | K43: 0
A44: Other Receivables(LTP) | B44: 13425.014 | C44: 8400 | D44: 6000 | E44: 3600 | F44: 366230 | G44: 414859.45 | H44: 538403.95 | I44: 582099.08 | J44: 713368.41 | K44: 633815.03
... A55: Prepayments suppliers | B55: 4325.962 | C55: 5259.34 | D55: 9137.686 | E55: 13886.014 | F55: 19320.138 | G55: 21138.777 | H55: 57656.905 | I55: 370969.18 | J55: 526988.56 | K55: 256446.7
A56: Total Inventories | B56: =SUM(B47:B53)+B55-B54 -> 22651.633 | C56: =SUM(C47:C53)+C55-C54 -> 23684.996 | D56: =SUM(D47:D53)+D55-D54 -> 31016.346 | E56: =SUM(E47:E53)+E55-E54 -> 44794.083 | F56: =SUM(F47:F53)+F55-F54 -> 53423.096 | G56: =SUM(G47:G53)+G55-G54 -> 51646.282 | H56: =SUM(H47:H53)+H55-H54 -> 105087.67 | I56: =SUM(I47:I53)+I55-I54 -> 610874.86 | ... K56: =SUM(K47:K53)+K55-K54 -> 946981.61
A57: Due from JVs & Partnerships | B57: 0 | C57: 0 | D57: 0 | E57: 0 | F57: 0 | G57: 0 | H57: 0 | I57: 0 | J57: 0 | K57: 0
A58: Due from Related Parties(CP) | B58: 0 | C58: 0 | D58: 0 | E58: 0 | F58: 0 | G58: 0 | H58: 0 | I58: 77608.136 | J58: 39712.709 | K58: 0
A59: Due from S'holder(CP) | B59: 0 | C59: 0 | D59: 1171.987 | E59: 0 | F59: 0 | G59: 0 | H59: 0 | I59: 0 | J59: 0 | K59: 0
A60: Short Term Securities | B60: 0 | C60: 0 | D60: 0 | E60: 0 | F60: 0 | G60: 0 | H60: 0 | I60: 0 | J60: 0 | K60: 0
A61: Secur & Other Fincl Assets(CP) | B61: 0 | C61: 0 | D61: 0 | E61: 0 | F61: 0 | G61: 0 | H61: 0 | I61: 0 | J61: 0 | K61: 0
A62: Deriv & Hedg Assets(CP) | B62: 0 | C62: 0 | D62: 0 | E62: 0 | F62: 0 | G62: 0 | H62: 0 | I62: 0 | J62: 0 | K62: 0
A63: Assets Plgd Under Securitization | B63: 0 | C63: 0 | D63: 0 | E63: 0 | F63: 0 | G63: 0 | H63: 0 | I63: 0 | J63: 0 | K63: 0
A64: Current Tax Receivables | B64: 60591.212 | C64: 0 | D64: 0 | E64: 0 | F64: 0 | G64: 0 | H64: 0 | I64: 0 | J64: 0 | K64: 0
A65: Prepayments(CP) | B65: 5085.024 | C65: 5342.574 | D65: 8909.682 | E65: 8927.35 | F65: 12011.114 | G65: 23050.475 | H65: 19066.82 | I65: 50807.63 | J65: 72914.236 | K65: 105966.15
A66: Assets Related to Disc Ops | B66: 0 | C66: 0 | D66: 0 | E66: 0 | F66: 0 | G66: 0 | H66: 0 | I66: 0 | J66: 0 | K66: 0
A67: Other Current Assets | B67: 489.49 | C67: 42053.057 | D67: 9450.712 | E67: 1701.426 | F67: 7443.861 | G67: 2058.644 | H67: 3778.442 | I67: 70971.119 | J67: 115595.52 | K67: 136131.59
A68: Cash unavailable or pledged | B68: 0 | C68: 0 | D68: 24.184 | E68: 0 | F68: 0 | G68: 24.547 | H68: 0 | I68: 45.347 | J68: 240.349 | K68: 245.015
... A70: Allow for Doubtful Accounts(-) | B70: 0 | C70: 0 | D70: 0 | E70: 4139.155 | F70: 4911.002 | G70: 7718.583 | H70: 20724.967 | I70: 34596.97 | J70: 67052.93 | K70: 75547.915
A71: Net Trade Receivables | B71: =+B69-B70 -> 27411.155 | C71: =+C69-C70 -> 41524.465 | D71: =+D69-D70 -> 54817.366 | E71: =+E69-E70 -> 70958.738 | F71: =+F69-F70 -> 52560.15 | G71: =+G69-G70 -> 66304.616 | H71: =+H69-H70 -> 86857.094 | I71: =+I69-I70 -> 428547.08 | ... K71: =+K69-K70 -> 976849.74
A72: Subscribed Capital-Called Not Paid | B72: 0 | C72: 0 | D72: 0 | E72: 0 | F72: 0 | G72: 0 | H72: 0 | I72: 0 | J72: 0 | K72: 0
A73: Other Receivables(CP) | B73: 0 | C73: 36024.808 | D73: 64114.995 | E73: 14729.85 | F73: 19531.399 | G73: 85507.247 | H73: 15886.799 | I73: 165508.36 | J73: 281208.97 | K73: 1341812.2
A74: Cash Equivalents | B74: 0 | C74: 0 | D74: 248.357 | E74: 0 | F74: 0 | G74: 0 | H74: 0 | I74: 6917.41 | J74: 0 | K74: 62284.552
A75: Cash in Hand and at Banks | B75: 49640.462 | C75: 25852.053 | D75: 18799.895 | E75: 85400.068 | F75: 92971.48 | G75: 209424.68 | H75: 212602.23 | I75: 692775.4 | J75: 822355.61 | K75: 2940424.1
A76: Common Share Capital | B76: 11000 | C76: 100000 | D76: 110000 | E76: 110000 | F76: 110000 | G76: 110000 | H76: 249999.89 | I76: 315000 | J76: 315000 | K76: 1000000
A77: Pref Share Capital | B77: 0 | C77: 0 | D77: 0 | E77: 0 | F77: 0 | G77: 0 | H77: 0 | I77: 0 | J77: 0 | K77: 0
A78: Share Premium | B78: 0 | C78: 0 | D78: 0 | E78: 0 | F78: 0 | G78: 0 | H78: 0 | I78: 0 | J78: 0 | K78: 0
A79: Special Items with Equity Character | B79: 0 | C79: 0 | D79: 0 | E79: 0 | F79: 0 | G79: 0 | H79: 0 | I79: 0 | J79: 0 | K79: 0
A80: Legal reserves | B80: 14632.387 | C80: 14415.212 | D80: 10501.536 | E80: 10879.715 | F80: 15582.38 | G80: 18842.764 | H80: 8945.538 | I80: 113676.95 | J80: 430013.35 | K80: 1111098.9
A81: Capital & Restricted Reserves | B81: 0 | C81: 0 | D81: 0 | E81: 0 | F81: 0 | G81: 0 | H81: 0 | I81: 0 | J81: 0 | K81: 0
A82: Permanent Equity | B82: =SUM(B76:B81) -> 25632.387 | C82: =SUM(C76:C81) -> 114415.21 | D82: =SUM(D76:D81) -> 120501.54 | E82: =SUM(E76:E81) -> 120879.71 | F82: =SUM(F76:F81) -> 125582.38 | G82: =SUM(G76:G81) -> 128842.76 | H82: =SUM(H76:H81) -> 258945.43 | I82: =SUM(I76:I81) -> 428676.95 | ... K82: =SUM(K76:K81) -> 2111098.9
A83: Revaluation Reserves | B83: 0 | C83: 0 | D83: 0 | E83: 0 | F83: 0 | G83: 0 | H83: 0 | I83: 5490472.3 | J83: 0 | K83: 0
A84: Consolidation reserves | B84: 0 | C84: 0 | D84: 0 | E84: 0 | F84: 0 | G84: 0 | H84: 0 | I84: 0 | J84: 0 | K84: 0
A85: Other Reserves | B85: 31611.131 | C85: 31611.131 | D85: 31611.131 | E85: 31611.131 | F85: 61611.131 | G85: 189682.85 | H85: 61611.131 | I85: 61611.131 | J85: 507988.07 | K85: 61611.131
A86: Retained Profits | B86: -28727.831 | C86: -100955.39 | D86: -108609.12 | E86: -111395.02 | F86: -97177.514 | G86: -248477.86 | H86: -264757.14 | I86: -97376.245 | J86: 8485686.8 | K86: 12686392
A87: Treasury Shares(-) | B87: 0 | C87: 0 | D87: 0 | E87: 0 | F87: 0 | G87: 0 | H87: 0 | I87: 0 | J87: 0 | K87: 0
A88: Forex Translation Equity | B88: 0 | C88: 0 | D88: 0 | E88: 0 | F88: 0 | G88: 0 | H88: 0 | I88: 0 | J88: 0 | K88: 0
A89: Subordinated Debt Equity | B89: 0 | C89: 0 | D89: 0 | E89: 0 | F89: 0 | G89: 0 | H89: 0 | I89: 0 | J89: 0 | K89: 0
A90: Deriv & Hedge adjust (+/-) | B90: 0 | C90: 0 | D90: 0 | E90: 0 | F90: 0 | G90: 0 | H90: 0 | I90: 0 | J90: 0 | K90: 0
A91: Other Equity | B91: -47332.566 | C91: -51445.915 | D91: -55020.631 | E91: -54897.86 | F91: -48360.951 | G91: -53779.846 | H91: -42922.023 | I91: -72628.244 | J91: 1064438.6 | K91: 2238693.6
A92: Accum Oth Eqty Rsrv Inc | B92: 0 | C92: 0 | D92: 0 | E92: 0 | F92: 0 | G92: 0 | H92: 0 | I92: 0 | J92: 0 | K92: 0
A93: Equity & Reserves | B93: =SUM(B83:B86)+SUM(B88:B92)-B87 -> -44449.266 | C93: =SUM(C83:C86)+SUM(C88:C92)-C87 -> -120790.18 | D93: =SUM(D83:D86)+SUM(D88:D92)-D87 -> -132018.62 | E93: =SUM(E83:E86)+SUM(E88:E92)-E87 -> -134681.75 | F93: =SUM(F83:F86)+SUM(F88:F92)-F87 -> -83927.334 | G93: =SUM(G83:G86)+SUM(G88:G92)-G87 -> -112574.86 | H93: =SUM(H83:H86)+SUM(H88:H92)-H87 -> -246068.03 | I93: =SUM(I83:I86)+SUM(I88:I92)-I87 -> 5382078.9 | ... K93: =SUM(K83:K86)+SUM(K88:K92)-K87 -> 14986697
A94: Minority Interest Equity | B94: 0 | C94: 0 | D94: 0 | E94: 0 | F94: 0 | G94: 0 | H94: 0 | I94: 0 | J94: 0 | K94: 0
A95: Deferred Income(LTP) | B95: 0 | C95: 4318.755 | D95: 3239.538 | E95: 0 | F95: 0 | G95: 0 | H95: 729.555 | I95: 2105.569 | J95: 2811.246 | K95: 90.217
A96: Restruct Provision(LTP) | B96: 0 | C96: 0 | D96: 0 | E96: 0 | F96: 0 | G96: 0 | H96: 0 | I96: 0 | J96: 0 | K96: 0
A97: Tax Provision(LTP) | B97: 0 | C97: 0 | D97: 0 | E97: 0 | F97: 0 | G97: 0 | H97: 0 | I97: 0 | J97: 0 | K97: 0
A98: Pension provision(LTP) | B98: 0 | C98: 0 | D98: 0 | E98: 0 | F98: 0 | G98: 0 | H98: 0 | I98: 0 | J98: 0 | K98: 0
A99: Other Provisions(LTP) | B99: 0 | C99: 0 | D99: 0 | E99: 0 | F99: 0 | G99: 0 | H99: 0 | I99: 0 | J99: 0 | K99: 0
A100: LT Provisions / Deferred Revenue | B100: =SUM(B95:B99) -> 0 | C100: =SUM(C95:C99) -> 4318.755 | D100: =SUM(D95:D99) -> 3239.538 | E100: =SUM(E95:E99) -> 0 | F100: =SUM(F95:F99) -> 0 | G100: =SUM(G95:G99) -> 0 | H100: =SUM(H95:H99) -> 729.555 | I100: =SUM(I95:I99) -> 2105.569 | ... K100: =SUM(K95:K99) -> 90.217
A101: LTD Bank | B101: 826913.1 | C101: 982649.84 | D101: 1037826.8 | E101: 1176102.7 | F101: 1632924.9 | G101: 1960840.1 | H101: 2259510.5 | I101: 3212352.8 | J101: 5001753.5 | K101: 11106978
A102: LTD Bonds | B102: 0 | C102: 0 | D102: 0 | E102: 0 | F102: 0 | G102: 0 | H102: 0 | I102: 0 | J102: 0 | K102: 0
A103: LTD Other | B103: 0 | C103: 0 | D103: 0 | E103: 0 | F103: 0 | G103: 0 | H103: 0 | I103: 0 | J103: 0 | K103: 0
A104: LTD Convertible | B104: 0 | C104: 0 | D104: 0 | E104: 0 | F104: 0 | G104: 0 | H104: 0 | I104: 0 | J104: 0 | K104: 0
A105: LTD Projects | B105: 0 | C105: 0 | D105: 0 | E105: 0 | F105: 0 | G105: 0 | H105: 0 | I105: 0 | J105: 0 | K105: 0
A106: LTD Subordinated | B106: 0 | C106: 0 | D106: 0 | E106: 0 | F106: 0 | G106: 0 | H106: 0 | I106: 0 | J106: 0 | K106: 0
A107: Finance Leases(LTP) | B107: 321.165 | C107: 0 | D107: 0 | E107: 0 | F107: 0 | G107: 0 | H107: 0 | I107: 0 | J107: 0 | K107: 0
A108: LT Banks / Bonds | B108: =SUM(B101:B107) -> 827234.27 | C108: =SUM(C101:C107) -> 982649.84 | D108: =SUM(D101:D107) -> 1037826.8 | E108: =SUM(E101:E107) -> 1176102.7 | F108: =SUM(F101:F107) -> 1632924.9 | G108: =SUM(G101:G107) -> 1960840.1 | H108: =SUM(H101:H107) -> 2259510.5 | I108: =SUM(I101:I107) -> 3212352.8 | ... K108: =SUM(K101:K107) -> 11106978
A109: Due to Related Parties(LTP) | B109: 137.1 | C109: 0 | D109: 0 | E109: 0 | F109: 0 | G109: 0 | H109: 0 | I109: 0 | J109: 0 | K109: 0
A110: Due to S'holder(LTP) | B110: 112371.11 | C110: 56488.429 | D110: 101366.06 | E110: 201118.39 | F110: 300972.53 | G110: 289046.15 | H110: 251409.27 | I110: 45297.967 | J110: 317742.57 | K110: 42702.573
A111: LT Group | B111: =SUM(B109:B110) -> 112508.21 | C111: =SUM(C109:C110) -> 56488.429 | D111: =SUM(D109:D110) -> 101366.06 | E111: =SUM(E109:E110) -> 201118.39 | F111: =SUM(F109:F110) -> 300972.53 | G111: =SUM(G109:G110) -> 289046.15 | H111: =SUM(H109:H110) -> 251409.27 | I111: =SUM(I109:I110) -> 45297.967 | ... K111: =SUM(K109:K110) -> 42702.573
...

Sheet FXs
A1: Yıl | B1: USD_Avg | C1: USD_End
A2: 2015 | B2: =+AVERAGE(Macro_Monthly!B2:B13) -> 2.7186517 | C2: =+Macro_Monthly!B13 -> 2.9172348
A3: 2016 | B3: =+AVERAGE(Macro_Monthly!B14:B25) -> 3.0185425 | C3: =+Macro_Monthly!B25 -> 3.4889273
A4: 2017 | B4: =+AVERAGE(Macro_Monthly!B26:B37) -> 3.6449402 | C4: =+Macro_Monthly!B37 -> 3.8477048
A5: 2018 | B5: =+AVERAGE(Macro_Monthly!B38:B49) -> 4.8259734 | C5: =+Macro_Monthly!B49 -> 5.3061238
A6: 2019 | B6: =+AVERAGE(Macro_Monthly!B50:B61) -> 5.6694745 | C6: =+Macro_Monthly!B61 -> 5.8376273
A7: 2020 | B7: =+AVERAGE(Macro_Monthly!B62:B73) -> 7.0055108 | C7: =+Macro_Monthly!B73 -> 7.7210652
A8: 2021 | B8: =+AVERAGE(Macro_Monthly!B74:B85) -> 8.831731 | C8: =+Macro_Monthly!B85 -> 13.528496
A9: 2022 | B9: =+AVERAGE(Macro_Monthly!B86:B97) -> 16.53621 | C9: =+Macro_Monthly!B97 -> 18.636968
A10: 2023 | B10: =+AVERAGE(Macro_Monthly!B98:B109) -> 23.693283 | C10: =+Macro_Monthly!B109 -> 29.022562
A11: 2024 | B11: =+AVERAGE(Macro_Monthly!B110:B121) -> 32.780165 | C11: =+Macro_Monthly!B121 -> 34.903823

Sheet converted2usd+IQR
B1: 2015 | C1: 2016 | D1: 2017 | E1: 2018 | F1: 2019 | G1: 2020 | H1: 2021 | I1: 2022 | J1: 2023 | K1: 2024 | L1: Q1 | M1: Q3 | N1: IQR | O1: Alt Sınır | P1: Üst Sınır
A2: Periods | B2: 12 | C2: 12 | D2: 12 | E2: 12 | F2: 12 | G2: 12 | H2: 12 | I2: 12 | J2: 12 | K2: 12
A3: Total Non-Current Assets | B3: =+Raw_Financials!B3/FXs!$C$2 -> 325069.25 | C3: =+Raw_Financials!C3/FXs!$C$3 -> 324618.71 | D3: =+Raw_Financials!D3/FXs!$C$4 -> 343542.28 | E3: =+Raw_Financials!E3/FXs!$C$5 -> 314017.38 | F3: =+Raw_Financials!F3/FXs!$C$6 -> 384257.64 | G3: =+Raw_Financials!G3/FXs!$C$7 -> 326367.29 | H3: =+Raw_Financials!H3/FXs!$C$8 -> 235364.53 | I3: =+Raw_Financials!I3/FXs!$C$9 -> 541429.79 | J3: =+Raw_Financials!J3/FXs!$C$10 -> 590914.77 | K3: =+Raw_Financials!K3/FXs!$C$11 -> 694328.07 | L3: =QUARTILE(B3:K3, 1) -> 324731.35 | M3: =QUARTILE(B3:K3, 3) -> 502136.76 | N3: =M3 - L3 -> 177405.41 | O3: =L3 - (3 * N3) -> -207484.88 | P3: =M3 + (3 * N3) -> 1034353
A4: Total Current Assets | B4: =+Raw_Financials!B4/FXs!$C$2 -> 56858.288 | C4: =+Raw_Financials!C4/FXs!$C$3 -> 50010.201 | D4: =+Raw_Financials!D4/FXs!$C$4 -> 49004.156 | E4: =+Raw_Financials!E4/FXs!$C$5 -> 42688.698 | F4: =+Raw_Financials!F4/FXs!$C$6 -> 40759.899 | G4: =+Raw_Financials!G4/FXs!$C$7 -> 56730.06 | H4: =+Raw_Financials!H4/FXs!$C$8 -> 32766.323 | I4: =+Raw_Financials!I4/FXs!$C$9 -> 112896.87 | J4: =+Raw_Financials!J4/FXs!$C$10 -> 106971.13 | K4: =+Raw_Financials!K4/FXs!$C$11 -> 186532.43 | L4: =QUARTILE(B4:K4, 1) -> 44267.562 | M4: =QUARTILE(B4:K4, 3) -> 94442.916 | N4: =M4 - L4 -> 50175.354 | O4: =L4 - (3 * N4) -> -106258.5 | P4: =M4 + (3 * N4) -> 244968.98
A5: Total Equity & Reserves | B5: =+Raw_Financials!B5/FXs!$C$2 -> -6450.245 | C5: =+Raw_Financials!C5/FXs!$C$3 -> -1827.1989 | D5: =+Raw_Financials!D5/FXs!$C$4 -> -2993.2359 | E5: =+Raw_Financials!E5/FXs!$C$5 -> -2601.1523 | F5: =+Raw_Financials!F5/FXs!$C$6 -> 7135.6125 | G5: =+Raw_Financials!G5/FXs!$C$7 -> 2106.9509 | H5: =+Raw_Financials!H5/FXs!$C$8 -> 951.87258 | I5: =+Raw_Financials!I5/FXs!$C$9 -> 311786.54 | J5: =+Raw_Financials!J5/FXs!$C$10 -> 372232.02 | K5: =+Raw_Financials!K5/FXs!$C$11 -> 489854.52 | L5: =QUARTILE(B5:K5, 1) -> -2407.6639 | M5: =QUARTILE(B5:K5, 3) -> 235623.81 | N5: =M5 - L5 -> 238031.47 | O5: =L5 - (3 * N5) -> -716502.09 | P5: =M5 + (3 * N5) -> 949718.23
A6: Total Non-Current Liabilities | B6: =+Raw_Financials!B6/FXs!$C$2 -> 325337.5 | C6: =+Raw_Financials!C6/FXs!$C$3 -> 300252.51 | D6: =+Raw_Financials!D6/FXs!$C$4 -> 297684.71 | E6: =+Raw_Financials!E6/FXs!$C$5 -> 259989.04 | F6: =+Raw_Financials!F6/FXs!$C$6 -> 331613.73 | G6: =+Raw_Financials!G6/FXs!$C$7 -> 291511.27 | H6: =+Raw_Financials!H6/FXs!$C$8 -> 185689.16 | I6: =+Raw_Financials!I6/FXs!$C$9 -> 174908.08 | J6: =+Raw_Financials!J6/FXs!$C$10 -> 183385.17 | K6: =+Raw_Financials!K6/FXs!$C$11 -> 319442.67 | L6: =QUARTILE(B6:K6, 1) -> 204264.13 | M6: =QUARTILE(B6:K6, 3) -> 314645.13 | N6: =M6 - L6 -> 110381 | O6: =L6 - (3 * N6) -> -126878.88 | P6: =M6 + (3 * N6) -> 645788.14
A7: Total Current Liabilities | B7: =+Raw_Financials!B7/FXs!$C$2 -> 60940.571 | C7: =+Raw_Financials!C7/FXs!$C$3 -> 76203.605 | D7: =+Raw_Financials!D7/FXs!$C$4 -> 97854.966 | E7: =+Raw_Financials!E7/FXs!$C$5 -> 99318.186 | F7: =+Raw_Financials!F7/FXs!$C$6 -> 86268.191 | G7: =+Raw_Financials!G7/FXs!$C$7 -> 89479.126 | H7: =+Raw_Financials!H7/FXs!$C$8 -> 81489.822 | I7: =+Raw_Financials!I7/FXs!$C$9 -> 167632.04 | J7: =+Raw_Financials!J7/FXs!$C$10 -> 142268.71 | K7: =+Raw_Financials!K7/FXs!$C$11 -> 71563.311 | L7: =QUARTILE(B7:K7, 1) -> 77525.159 | M7: =QUARTILE(B7:K7, 3) -> 98952.381 | N7: =M7 - L7 -> 21427.222 | O7: =L7 - (3 * N7) -> 13243.494 | P7: =M7 + (3 * N7) -> 163234.05
A8: Total Income & Expenses | B8: =+Raw_Financials!B8/FXs!$C$2 -> 97450.616 | C8: =+Raw_Financials!C8/FXs!$C$3 -> -20675.063 | D8: =+Raw_Financials!D8/FXs!$C$4 -> -1989.1677 | E8: =+Raw_Financials!E8/FXs!$C$5 -> -525.03449 | F8: =+Raw_Financials!F8/FXs!$C$6 -> 2608.6133 | G8: =+Raw_Financials!G8/FXs!$C$7 -> -19485.826 | H8: =+Raw_Financials!H8/FXs!$C$8 -> -1203.3321 | I8: =+Raw_Financials!I8/FXs!$C$9 -> 8981.1225 | J8: =+Raw_Financials!J8/FXs!$C$10 -> -2255.0462 | K8: =+Raw_Financials!K8/FXs!$C$11 -> 31851.185 | L8: =QUARTILE(B8:K8, 1) -> -2188.5766 | M8: =QUARTILE(B8:K8, 3) -> 7387.9952 | N8: =M8 - L8 -> 9576.5718 | O8: =L8 - (3 * N8) -> -30918.292 | P8: =M8 + (3 * N8) -> 36117.711
A9: Total Assets | B9: =+Raw_Financials!B9/FXs!$C$2 -> 381927.54 | C9: =+Raw_Financials!C9/FXs!$C$3 -> 374628.91 | D9: =+Raw_Financials!D9/FXs!$C$4 -> 392546.43 | E9: =+Raw_Financials!E9/FXs!$C$5 -> 356706.08 | F9: =+Raw_Financials!F9/FXs!$C$6 -> 425017.54 | G9: =+Raw_Financials!G9/FXs!$C$7 -> 383097.35 | H9: =+Raw_Financials!H9/FXs!$C$8 -> 268130.85 | I9: =+Raw_Financials!I9/FXs!$C$9 -> 654326.66 | J9: =+Raw_Financials!J9/FXs!$C$10 -> 697885.9 | K9: =+Raw_Financials!K9/FXs!$C$11 -> 880860.51 | L9: =QUARTILE(B9:K9, 1) -> 376453.57 | M9: =QUARTILE(B9:K9, 3) -> 596999.38 | N9: =M9 - L9 -> 220545.81 | O9: =L9 - (3 * N9) -> -285183.87 | P9: =M9 + (3 * N9) -> 1258636.8
A10: Total Liabs & Net Worth | B10: =+Raw_Financials!B10/FXs!$C$2 -> 379827.82 | C10: =+Raw_Financials!C10/FXs!$C$3 -> 374628.91 | D10: =+Raw_Financials!D10/FXs!$C$4 -> 392546.44 | E10: =+Raw_Financials!E10/FXs!$C$5 -> 356706.08 | F10: =+Raw_Financials!F10/FXs!$C$6 -> 425017.54 | G10: =+Raw_Financials!G10/FXs!$C$7 -> 383097.35 | H10: =+Raw_Financials!H10/FXs!$C$8 -> 268130.85 | I10: =+Raw_Financials!I10/FXs!$C$9 -> 654326.66 | J10: =+Raw_Financials!J10/FXs!$C$10 -> 697885.9 | K10: =+Raw_Financials!K10/FXs!$C$11 -> 880860.51 | L10: =QUARTILE(B10:K10, 1) -> 375928.64 | M10: =QUARTILE(B10:K10, 3) -> 596999.38 | N10: =M10 - L10 -> 221070.74 | O10: =L10 - (3 * N10) -> -287283.59 | P10: =M10 + (3 * N10) -> 1260211.6
A11: Land | B11: =+Raw_Financials!B11/FXs!$C$2 -> 4810.2632 | C11: =+Raw_Financials!C11/FXs!$C$3 -> 4022.0578 | D11: =+Raw_Financials!D11/FXs!$C$4 -> 6082.4113 | E11: =+Raw_Financials!E11/FXs!$C$5 -> 6230.6034 | F11: =+Raw_Financials!F11/FXs!$C$6 -> 17790.25 | G11: =+Raw_Financials!G11/FXs!$C$7 -> 13117.244 | H11: =+Raw_Financials!H11/FXs!$C$8 -> 7315.5727 | I11: =+Raw_Financials!I11/FXs!$C$9 -> 6453.7354 | J11: =+Raw_Financials!J11/FXs!$C$10 -> 10024.251 | K11: =+Raw_Financials!K11/FXs!$C$11 -> 12851.248 | L11: =QUARTILE(B11:K11, 1) -> 6119.4593 | M11: =QUARTILE(B11:K11, 3) -> 12144.499 | N11: =M11 - L11 -> 6025.0392 | O11: =L11 - (3 * N11) -> -11955.658 | P11: =M11 + (3 * N11) -> 30219.616
A12: Buildings | B12: =+Raw_Financials!B12/FXs!$C$2 -> 285805.63 | C12: =+Raw_Financials!C12/FXs!$C$3 -> 299048.97 | D12: =+Raw_Financials!D12/FXs!$C$4 -> 327697.8 | E12: =+Raw_Financials!E12/FXs!$C$5 -> 304895.62 | F12: =+Raw_Financials!F12/FXs!$C$6 -> 309085.66 | G12: =+Raw_Financials!G12/FXs!$C$7 -> 269166.68 | H12: =+Raw_Financials!H12/FXs!$C$8 -> 189077.71 | I12: =+Raw_Financials!I12/FXs!$C$9 -> 385983.76 | J12: =+Raw_Financials!J12/FXs!$C$10 -> 466023.22 | K12: =+Raw_Financials!K12/FXs!$C$11 -> 486355.39 | L12: =QUARTILE(B12:K12, 1) -> 289116.46 | M12: =QUARTILE(B12:K12, 3) -> 371412.27 | N12: =M12 - L12 -> 82295.808 | O12: =L12 - (3 * N12) -> 42229.039 | P12: =M12 + (3 * N12) -> 618299.7
A13: Leasehold Improvements | B13: =+Raw_Financials!B13/FXs!$C$2 -> 481.1128 | C13: =+Raw_Financials!C13/FXs!$C$3 -> 409.01884 | D13: =+Raw_Financials!D13/FXs!$C$4 -> 530.54253 | E13: =+Raw_Financials!E13/FXs!$C$5 -> 512.96504 | F13: =+Raw_Financials!F13/FXs!$C$6 -> 590.65779 | G13: =+Raw_Financials!G13/FXs!$C$7 -> 447.25564 | H13: =+Raw_Financials!H13/FXs!$C$8 -> 259.55037 | I13: =+Raw_Financials!I13/FXs!$C$9 -> 1069.1242 | J13: =+Raw_Financials!J13/FXs!$C$10 -> 885.67205 | K13: =+Raw_Financials!K13/FXs!$C$11 -> 822.52423 | L13: =QUARTILE(B13:K13, 1) -> 455.71993 | M13: =QUARTILE(B13:K13, 3) -> 764.55762 | N13: =M13 - L13 -> 308.83769 | O13: =L13 - (3 * N13) -> -470.79313 | P13: =M13 + (3 * N13) -> 1691.0707
A14: Plant & Equipment | B14: =+Raw_Financials!B14/FXs!$C$2 -> 7177.9176 | C14: =+Raw_Financials!C14/FXs!$C$3 -> 7260.9834 | D14: =+Raw_Financials!D14/FXs!$C$4 -> 7710.2906 | E14: =+Raw_Financials!E14/FXs!$C$5 -> 6540.977 | F14: =+Raw_Financials!F14/FXs!$C$6 -> 6282.6927 | G14: =+Raw_Financials!G14/FXs!$C$7 -> 5355.8385 | H14: =+Raw_Financials!H14/FXs!$C$8 -> 3636.4045 | I14: =+Raw_Financials!I14/FXs!$C$9 -> 11539.079 | J14: =+Raw_Financials!J14/FXs!$C$10 -> 12689.894 | K14: =+Raw_Financials!K14/FXs!$C$11 -> 12386.308 | L14: =QUARTILE(B14:K14, 1) -> 6347.2638 | M14: =QUARTILE(B14:K14, 3) -> 10581.882 | N14: =M14 - L14 -> 4234.6185 | O14: =L14 - (3 * N14) -> -6356.5918 | P14: =M14 + (3 * N14) -> 23285.738
... A225: Minority Interests | B225: =+Raw_Financials!B225/FXs!$C$2 -> 0 | C225: =+Raw_Financials!C225/FXs!$C$3 -> 0 | D225: =+Raw_Financials!D225/FXs!$C$4 -> 0 | E225: =+Raw_Financials!E225/FXs!$C$5 -> 0 | F225: =+Raw_Financials!F225/FXs!$C$6 -> 0 | G225: =+Raw_Financials!G225/FXs!$C$7 -> 0 | H225: =+Raw_Financials!H225/FXs!$C$8 -> 0 | I225: =+Raw_Financials!I225/FXs!$C$9 -> 0 | J225: =+Raw_Financials!J225/FXs!$C$10 -> 0 | K225: =+Raw_Financials!K225/FXs!$C$11 -> 0 | L225: =QUARTILE(B225:K225, 1) -> 0 | M225: =QUARTILE(B225:K225, 3) -> 0 | N225: =M225 - L225 -> 0 | O225: =L225 - (3 * N225) -> 0 | P225: =M225 + (3 * N225) -> 0

Sheet IQR_results_usd
B1: 2015 | C1: 2016 | D1: 2017 | E1: 2018 | F1: 2019 | G1: 2020 | H1: 2021 | I1: 2022 | J1: 2023 | K1: 2024
A2: Periods | B2: 12 | C2: 12 | D2: 12 | E2: 12 | F2: 12 | G2: 12 | H2: 12 | I2: 12 | J2: 12 | K2: 12
A3: Total Non-Current Assets | B3: =MEDIAN('converted2usd+IQR'!B3, 'converted2usd+IQR'!$O3, 'converted2usd+IQR'!$P3) -> 325069.25 | C3: =MEDIAN('converted2usd+IQR'!C3, 'converted2usd+IQR'!$O3, 'converted2usd+IQR'!$P3) -> 324618.71 | D3: =MEDIAN('converted2usd+IQR'!D3, 'converted2usd+IQR'!$O3, 'converted2usd+IQR'!$P3) -> 343542.28 | E3: =MEDIAN('converted2usd+IQR'!E3, 'converted2usd+IQR'!$O3, 'converted2usd+IQR'!$P3) -> 314017.38 | F3: =MEDIAN('converted2usd+IQR'!F3, 'converted2usd+IQR'!$O3, 'converted2usd+IQR'!$P3) -> 384257.64 | G3: =MEDIAN('converted2usd+IQR'!G3, 'converted2usd+IQR'!$O3, 'converted2usd+IQR'!$P3) -> 326367.29 | H3: =MEDIAN('converted2usd+IQR'!H3, 'converted2usd+IQR'!$O3, 'converted2usd+IQR'!$P3) -> 235364.53 | I3: =MEDIAN('converted2usd+IQR'!I3, 'converted2usd+IQR'!$O3, 'converted2usd+IQR'!$P3) -> 541429.79 | ... K3: =MEDIAN('converted2usd+IQR'!K3, 'converted2usd+IQR'!$O3, 'converted2usd+IQR'!$P3) -> 694328.07
A4: Total Current Assets | B4: =MEDIAN('converted2usd+IQR'!B4, 'converted2usd+IQR'!$O4, 'converted2usd+IQR'!$P4) -> 56858.288 | C4: =MEDIAN('converted2usd+IQR'!C4, 'converted2usd+IQR'!$O4, 'converted2usd+IQR'!$P4) -> 50010.201 | D4: =MEDIAN('converted2usd+IQR'!D4, 'converted2usd+IQR'!$O4, 'converted2usd+IQR'!$P4) -> 49004.156 | E4: =MEDIAN('converted2usd+IQR'!E4, 'converted2usd+IQR'!$O4, 'converted2usd+IQR'!$P4) -> 42688.698 | F4: =MEDIAN('converted2usd+IQR'!F4, 'converted2usd+IQR'!$O4, 'converted2usd+IQR'!$P4) -> 40759.899 | G4: =MEDIAN('converted2usd+IQR'!G4, 'converted2usd+IQR'!$O4, 'converted2usd+IQR'!$P4) -> 56730.06 | H4: =MEDIAN('converted2usd+IQR'!H4, 'converted2usd+IQR'!$O4, 'converted2usd+IQR'!$P4) -> 32766.323 | I4: =MEDIAN('converted2usd+IQR'!I4, 'converted2usd+IQR'!$O4, 'converted2usd+IQR'!$P4) -> 112896.87 | ... K4: =MEDIAN('converted2usd+IQR'!K4, 'converted2usd+IQR'!$O4, 'converted2usd+IQR'!$P4) -> 186532.43
A5: Total Equity & Reserves | B5: =MEDIAN('converted2usd+IQR'!B5, 'converted2usd+IQR'!$O5, 'converted2usd+IQR'!$P5) -> -6450.245 | C5: =MEDIAN('converted2usd+IQR'!C5, 'converted2usd+IQR'!$O5, 'converted2usd+IQR'!$P5) -> -1827.1989 | D5: =MEDIAN('converted2usd+IQR'!D5, 'converted2usd+IQR'!$O5, 'converted2usd+IQR'!$P5) -> -2993.2359 | E5: =MEDIAN('converted2usd+IQR'!E5, 'converted2usd+IQR'!$O5, 'converted2usd+IQR'!$P5) -> -2601.1523 | F5: =MEDIAN('converted2usd+IQR'!F5, 'converted2usd+IQR'!$O5, 'converted2usd+IQR'!$P5) -> 7135.6125 | G5: =MEDIAN('converted2usd+IQR'!G5, 'converted2usd+IQR'!$O5, 'converted2usd+IQR'!$P5) -> 2106.9509 | H5: =MEDIAN('converted2usd+IQR'!H5, 'converted2usd+IQR'!$O5, 'converted2usd+IQR'!$P5) -> 951.87258 | I5: =MEDIAN('converted2usd+IQR'!I5, 'converted2usd+IQR'!$O5, 'converted2usd+IQR'!$P5) -> 311786.54 | ... K5: =MEDIAN('converted2usd+IQR'!K5, 'converted2usd+IQR'!$O5, 'converted2usd+IQR'!$P5) -> 489854.52
A6: Total Non-Current Liabilities | B6: =MEDIAN('converted2usd+IQR'!B6, 'converted2usd+IQR'!$O6, 'converted2usd+IQR'!$P6) -> 325337.5 | C6: =MEDIAN('converted2usd+IQR'!C6, 'converted2usd+IQR'!$O6, 'converted2usd+IQR'!$P6) -> 300252.51 | D6: =MEDIAN('converted2usd+IQR'!D6, 'converted2usd+IQR'!$O6, 'converted2usd+IQR'!$P6) -> 297684.71 | E6: =MEDIAN('converted2usd+IQR'!E6, 'converted2usd+IQR'!$O6, 'converted2usd+IQR'!$P6) -> 259989.04 | F6: =MEDIAN('converted2usd+IQR'!F6, 'converted2usd+IQR'!$O6, 'converted2usd+IQR'!$P6) -> 331613.73 | G6: =MEDIAN('converted2usd+IQR'!G6, 'converted2usd+IQR'!$O6, 'converted2usd+IQR'!$P6) -> 291511.27 | H6: =MEDIAN('converted2usd+IQR'!H6, 'converted2usd+IQR'!$O6, 'converted2usd+IQR'!$P6) -> 185689.16 | I6: =MEDIAN('converted2usd+IQR'!I6, 'converted2usd+IQR'!$O6, 'converted2usd+IQR'!$P6) -> 174908.08 | ... K6: =MEDIAN('converted2usd+IQR'!K6, 'converted2usd+IQR'!$O6, 'converted2usd+IQR'!$P6) -> 319442.67
A7: Total Current Liabilities | B7: =MEDIAN('converted2usd+IQR'!B7, 'converted2usd+IQR'!$O7, 'converted2usd+IQR'!$P7) -> 60940.571 | C7: =MEDIAN('converted2usd+IQR'!C7, 'converted2usd+IQR'!$O7, 'converted2usd+IQR'!$P7) -> 76203.605 | D7: =MEDIAN('converted2usd+IQR'!D7, 'converted2usd+IQR'!$O7, 'converted2usd+IQR'!$P7) -> 97854.966 | E7: =MEDIAN('converted2usd+IQR'!E7, 'converted2usd+IQR'!$O7, 'converted2usd+IQR'!$P7) -> 99318.186 | F7: =MEDIAN('converted2usd+IQR'!F7, 'converted2usd+IQR'!$O7, 'converted2usd+IQR'!$P7) -> 86268.191 | G7: =MEDIAN('converted2usd+IQR'!G7, 'converted2usd+IQR'!$O7, 'converted2usd+IQR'!$P7) -> 89479.126 | H7: =MEDIAN('converted2usd+IQR'!H7, 'converted2usd+IQR'!$O7, 'converted2usd+IQR'!$P7) -> 81489.822 | I7: =MEDIAN('converted2usd+IQR'!I7, 'converted2usd+IQR'!$O7, 'converted2usd+IQR'!$P7) -> 163234.05 | ... K7: =MEDIAN('converted2usd+IQR'!K7, 'converted2usd+IQR'!$O7, 'converted2usd+IQR'!$P7) -> 71563.311
A8: Total Income & Expenses | B8: =MEDIAN('converted2usd+IQR'!B8, 'converted2usd+IQR'!$O8, 'converted2usd+IQR'!$P8) -> 36117.711 | C8: =MEDIAN('converted2usd+IQR'!C8, 'converted2usd+IQR'!$O8, 'converted2usd+IQR'!$P8) -> -20675.063 | D8: =MEDIAN('converted2usd+IQR'!D8, 'converted2usd+IQR'!$O8, 'converted2usd+IQR'!$P8) -> -1989.1677 | E8: =MEDIAN('converted2usd+IQR'!E8, 'converted2usd+IQR'!$O8, 'converted2usd+IQR'!$P8) -> -525.03449 | F8: =MEDIAN('converted2usd+IQR'!F8, 'converted2usd+IQR'!$O8, 'converted2usd+IQR'!$P8) -> 2608.6133 | G8: =MEDIAN('converted2usd+IQR'!G8, 'converted2usd+IQR'!$O8, 'converted2usd+IQR'!$P8) -> -19485.826 | H8: =MEDIAN('converted2usd+IQR'!H8, 'converted2usd+IQR'!$O8, 'converted2usd+IQR'!$P8) -> -1203.3321 | I8: =MEDIAN('converted2usd+IQR'!I8, 'converted2usd+IQR'!$O8, 'converted2usd+IQR'!$P8) -> 8981.1225 | ... K8: =MEDIAN('converted2usd+IQR'!K8, 'converted2usd+IQR'!$O8, 'converted2usd+IQR'!$P8) -> 31851.185
A9: Total Assets | B9: =MEDIAN('converted2usd+IQR'!B9, 'converted2usd+IQR'!$O9, 'converted2usd+IQR'!$P9) -> 381927.54 | C9: =MEDIAN('converted2usd+IQR'!C9, 'converted2usd+IQR'!$O9, 'converted2usd+IQR'!$P9) -> 374628.91 | D9: =MEDIAN('converted2usd+IQR'!D9, 'converted2usd+IQR'!$O9, 'converted2usd+IQR'!$P9) -> 392546.43 | E9: =MEDIAN('converted2usd+IQR'!E9, 'converted2usd+IQR'!$O9, 'converted2usd+IQR'!$P9) -> 356706.08 | F9: =MEDIAN('converted2usd+IQR'!F9, 'converted2usd+IQR'!$O9, 'converted2usd+IQR'!$P9) -> 425017.54 | G9: =MEDIAN('converted2usd+IQR'!G9, 'converted2usd+IQR'!$O9, 'converted2usd+IQR'!$P9) -> 383097.35 | H9: =MEDIAN('converted2usd+IQR'!H9, 'converted2usd+IQR'!$O9, 'converted2usd+IQR'!$P9) -> 268130.85 | I9: =MEDIAN('converted2usd+IQR'!I9, 'converted2usd+IQR'!$O9, 'converted2usd+IQR'!$P9) -> 654326.66 | ... K9: =MEDIAN('converted2usd+IQR'!K9, 'converted2usd+IQR'!$O9, 'converted2usd+IQR'!$P9) -> 880860.51
A10: Total Liabs & Net Worth | B10: =MEDIAN('converted2usd+IQR'!B10, 'converted2usd+IQR'!$O10, 'converted2usd+IQR'!$P10) -> 379827.82 | C10: =MEDIAN('converted2usd+IQR'!C10, 'converted2usd+IQR'!$O10, 'converted2usd+IQR'!$P10) -> 374628.91 | D10: =MEDIAN('converted2usd+IQR'!D10, 'converted2usd+IQR'!$O10, 'converted2usd+IQR'!$P10) -> 392546.44 | E10: =MEDIAN('converted2usd+IQR'!E10, 'converted2usd+IQR'!$O10, 'converted2usd+IQR'!$P10) -> 356706.08 | F10: =MEDIAN('converted2usd+IQR'!F10, 'converted2usd+IQR'!$O10, 'converted2usd+IQR'!$P10) -> 425017.54 | G10: =MEDIAN('converted2usd+IQR'!G10, 'converted2usd+IQR'!$O10, 'converted2usd+IQR'!$P10) -> 383097.35 | H10: =MEDIAN('converted2usd+IQR'!H10, 'converted2usd+IQR'!$O10, 'converted2usd+IQR'!$P10) -> 268130.85 | I10: =MEDIAN('converted2usd+IQR'!I10, 'converted2usd+IQR'!$O10, 'converted2usd+IQR'!$P10) -> 654326.66 | ... K10: =MEDIAN('converted2usd+IQR'!K10, 'converted2usd+IQR'!$O10, 'converted2usd+IQR'!$P10) -> 880860.51
A11: Land | B11: =MEDIAN('converted2usd+IQR'!B11, 'converted2usd+IQR'!$O11, 'converted2usd+IQR'!$P11) -> 4810.2632 | C11: =MEDIAN('converted2usd+IQR'!C11, 'converted2usd+IQR'!$O11, 'converted2usd+IQR'!$P11) -> 4022.0578 | D11: =MEDIAN('converted2usd+IQR'!D11, 'converted2usd+IQR'!$O11, 'converted2usd+IQR'!$P11) -> 6082.4113 | E11: =MEDIAN('converted2usd+IQR'!E11, 'converted2usd+IQR'!$O11, 'converted2usd+IQR'!$P11) -> 6230.6034 | F11: =MEDIAN('converted2usd+IQR'!F11, 'converted2usd+IQR'!$O11, 'converted2usd+IQR'!$P11) -> 17790.25 | G11: =MEDIAN('converted2usd+IQR'!G11, 'converted2usd+IQR'!$O11, 'converted2usd+IQR'!$P11) -> 13117.244 | H11: =MEDIAN('converted2usd+IQR'!H11, 'converted2usd+IQR'!$O11, 'converted2usd+IQR'!$P11) -> 7315.5727 | I11: =MEDIAN('converted2usd+IQR'!I11, 'converted2usd+IQR'!$O11, 'converted2usd+IQR'!$P11) -> 6453.7354 | ... K11: =MEDIAN('converted2usd+IQR'!K11, 'converted2usd+IQR'!$O11, 'converted2usd+IQR'!$P11) -> 12851.248
A12: Buildings | B12: =MEDIAN('converted2usd+IQR'!B12, 'converted2usd+IQR'!$O12, 'converted2usd+IQR'!$P12) -> 285805.63 | C12: =MEDIAN('converted2usd+IQR'!C12, 'converted2usd+IQR'!$O12, 'converted2usd+IQR'!$P12) -> 299048.97 | D12: =MEDIAN('converted2usd+IQR'!D12, 'converted2usd+IQR'!$O12, 'converted2usd+IQR'!$P12) -> 327697.8 | E12: =MEDIAN('converted2usd+IQR'!E12, 'converted2usd+IQR'!$O12, 'converted2usd+IQR'!$P12) -> 304895.62 | F12: =MEDIAN('converted2usd+IQR'!F12, 'converted2usd+IQR'!$O12, 'converted2usd+IQR'!$P12) -> 309085.66 | G12: =MEDIAN('converted2usd+IQR'!G12, 'converted2usd+IQR'!$O12, 'converted2usd+IQR'!$P12) -> 269166.68 | H12: =MEDIAN('converted2usd+IQR'!H12, 'converted2usd+IQR'!$O12, 'converted2usd+IQR'!$P12) -> 189077.71 | I12: =MEDIAN('converted2usd+IQR'!I12, 'converted2usd+IQR'!$O12, 'converted2usd+IQR'!$P12) -> 385983.76 | ... K12: =MEDIAN('converted2usd+IQR'!K12, 'converted2usd+IQR'!$O12, 'converted2usd+IQR'!$P12) -> 486355.39
A13: Leasehold Improvements | B13: =MEDIAN('converted2usd+IQR'!B13, 'converted2usd+IQR'!$O13, 'converted2usd+IQR'!$P13) -> 481.1128 | C13: =MEDIAN('converted2usd+IQR'!C13, 'converted2usd+IQR'!$O13, 'converted2usd+IQR'!$P13) -> 409.01884 | D13: =MEDIAN('converted2usd+IQR'!D13, 'converted2usd+IQR'!$O13, 'converted2usd+IQR'!$P13) -> 530.54253 | E13: =MEDIAN('converted2usd+IQR'!E13, 'converted2usd+IQR'!$O13, 'converted2usd+IQR'!$P13) -> 512.96504 | F13: =MEDIAN('converted2usd+IQR'!F13, 'converted2usd+IQR'!$O13, 'converted2usd+IQR'!$P13) -> 590.65779 | G13: =MEDIAN('converted2usd+IQR'!G13, 'converted2usd+IQR'!$O13, 'converted2usd+IQR'!$P13) -> 447.25564 | H13: =MEDIAN('converted2usd+IQR'!H13, 'converted2usd+IQR'!$O13, 'converted2usd+IQR'!$P13) -> 259.55037 | I13: =MEDIAN('converted2usd+IQR'!I13, 'converted2usd+IQR'!$O13, 'converted2usd+IQR'!$P13) -> 1069.1242 | ... K13: =MEDIAN('converted2usd+IQR'!K13, 'converted2usd+IQR'!$O13, 'converted2usd+IQR'!$P13) -> 822.52423
A14: Plant & Equipment | B14: =MEDIAN('converted2usd+IQR'!B14, 'converted2usd+IQR'!$O14, 'converted2usd+IQR'!$P14) -> 7177.9176 | C14: =MEDIAN('converted2usd+IQR'!C14, 'converted2usd+IQR'!$O14, 'converted2usd+IQR'!$P14) -> 7260.9834 | D14: =MEDIAN('converted2usd+IQR'!D14, 'converted2usd+IQR'!$O14, 'converted2usd+IQR'!$P14) -> 7710.2906 | E14: =MEDIAN('converted2usd+IQR'!E14, 'converted2usd+IQR'!$O14, 'converted2usd+IQR'!$P14) -> 6540.977 | F14: =MEDIAN('converted2usd+IQR'!F14, 'converted2usd+IQR'!$O14, 'converted2usd+IQR'!$P14) -> 6282.6927 | G14: =MEDIAN('converted2usd+IQR'!G14, 'converted2usd+IQR'!$O14, 'converted2usd+IQR'!$P14) -> 5355.8385 | H14: =MEDIAN('converted2usd+IQR'!H14, 'converted2usd+IQR'!$O14, 'converted2usd+IQR'!$P14) -> 3636.4045 | I14: =MEDIAN('converted2usd+IQR'!I14, 'converted2usd+IQR'!$O14, 'converted2usd+IQR'!$P14) -> 11539.079 | ... K14: =MEDIAN('converted2usd+IQR'!K14, 'converted2usd+IQR'!$O14, 'converted2usd+IQR'!$P14) -> 12386.308
... A225: Minority Interests | B225: =MEDIAN('converted2usd+IQR'!B225, 'converted2usd+IQR'!$O225, 'converted2usd+IQR'!$P225) -> 0 | C225: =MEDIAN('converted2usd+IQR'!C225, 'converted2usd+IQR'!$O225, 'converted2usd+IQR'!$P225) -> 0 | D225: =MEDIAN('converted2usd+IQR'!D225, 'converted2usd+IQR'!$O225, 'converted2usd+IQR'!$P225) -> 0 | E225: =MEDIAN('converted2usd+IQR'!E225, 'converted2usd+IQR'!$O225, 'converted2usd+IQR'!$P225) -> 0 | F225: =MEDIAN('converted2usd+IQR'!F225, 'converted2usd+IQR'!$O225, 'converted2usd+IQR'!$P225) -> 0 | G225: =MEDIAN('converted2usd+IQR'!G225, 'converted2usd+IQR'!$O225, 'converted2usd+IQR'!$P225) -> 0 | H225: =MEDIAN('converted2usd+IQR'!H225, 'converted2usd+IQR'!$O225, 'converted2usd+IQR'!$P225) -> 0 | I225: =MEDIAN('converted2usd+IQR'!I225, 'converted2usd+IQR'!$O225, 'converted2usd+IQR'!$P225) -> 0 | ... K225: =MEDIAN('converted2usd+IQR'!K225, 'converted2usd+IQR'!$O225, 'converted2usd+IQR'!$P225) -> 0

Sheet final_results
B1: 2015 | C1: 2016 | D1: 2017 | E1: 2018 | F1: 2019 | G1: 2020 | H1: 2021 | I1: 2022 | J1: 2023 | K1: 2024
A2: Periods | B2: 12 | C2: 12 | D2: 12 | E2: 12 | F2: 12 | G2: 12 | H2: 12 | I2: 12 | J2: 12 | K2: 12
A3: Total Non-Current Assets | B3: =+IQR_results_usd!B3*FXs!$C$2 -> 948303.32 | C3: =+IQR_results_usd!C3*FXs!$C$3 -> 1132571.1 | D3: =+IQR_results_usd!D3*FXs!$C$4 -> 1321849.3 | E3: =+IQR_results_usd!E3*FXs!$C$5 -> 1666215.1 | F3: =+IQR_results_usd!F3*FXs!$C$6 -> 2243152.9 | G3: =+IQR_results_usd!G3*FXs!$C$7 -> 2519903.1 | H3: =+IQR_results_usd!H3*FXs!$C$8 -> 3184128 | I3: =+IQR_results_usd!I3*FXs!$C$9 -> 10090610 | J3: =+IQR_results_usd!J3*FXs!$C$10 -> 17149861 | K3: =+IQR_results_usd!K3*FXs!$C$11 -> 24234704
A4: Total Current Assets | B4: =+IQR_results_usd!B4*FXs!$C$2 -> 165868.98 | C4: =+IQR_results_usd!C4*FXs!$C$3 -> 174481.95 | D4: =+IQR_results_usd!D4*FXs!$C$4 -> 188553.52 | E4: =+IQR_results_usd!E4*FXs!$C$5 -> 226511.52 | F4: =+IQR_results_usd!F4*FXs!$C$6 -> 237941.1 | G4: =+IQR_results_usd!G4*FXs!$C$7 -> 438016.49 | H4: =+IQR_results_usd!H4*FXs!$C$8 -> 443279.05 | I4: =+IQR_results_usd!I4*FXs!$C$9 -> 2104055.3 | J4: =+IQR_results_usd!J4*FXs!$C$10 -> 3104576.1 | K4: =+IQR_results_usd!K4*FXs!$C$11 -> 6510695 | M4: bu sheet'teki veriler modelde kullanılacak
A5: Total Equity & Reserves | B5: =+IQR_results_usd!B5*FXs!$C$2 -> -18816.879 | C5: =+IQR_results_usd!C5*FXs!$C$3 -> -6374.964 | D5: =+IQR_results_usd!D5*FXs!$C$4 -> -11517.088 | E5: =+IQR_results_usd!E5*FXs!$C$5 -> -13802.036 | F5: =+IQR_results_usd!F5*FXs!$C$6 -> 41655.046 | G5: =+IQR_results_usd!G5*FXs!$C$7 -> 16267.905 | H5: =+IQR_results_usd!H5*FXs!$C$8 -> 12877.404 | I5: =+IQR_results_usd!I5*FXs!$C$9 -> 5810755.9 | J5: =+IQR_results_usd!J5*FXs!$C$10 -> 10803127 | K5: =+IQR_results_usd!K5*FXs!$C$11 -> 17097795 | M5: Genel tabloda toplam 2240 hücrenin 73 tanesi değişmiş; bunun 68’i üst sınır, 3’ü alt sınır kırpması.
A6: Total Non-Current Liabilities | B6: =+IQR_results_usd!B6*FXs!$C$2 -> 949085.87 | C6: =+IQR_results_usd!C6*FXs!$C$3 -> 1047559.2 | D6: =+IQR_results_usd!D6*FXs!$C$4 -> 1145402.9 | E6: =+IQR_results_usd!E6*FXs!$C$5 -> 1379534.1 | F6: =+IQR_results_usd!F6*FXs!$C$6 -> 1935837.4 | G6: =+IQR_results_usd!G6*FXs!$C$7 -> 2250777.5 | H6: =+IQR_results_usd!H6*FXs!$C$8 -> 2512094.9 | I6: =+IQR_results_usd!I6*FXs!$C$9 -> 3259756.4 | J6: =+IQR_results_usd!J6*FXs!$C$10 -> 5322307.3 | K6: =+IQR_results_usd!K6*FXs!$C$11 -> 11149770
A7: Total Current Liabilities | B7: =+IQR_results_usd!B7*FXs!$C$2 -> 177777.95 | C7: =+IQR_results_usd!C7*FXs!$C$3 -> 265868.83 | D7: =+IQR_results_usd!D7*FXs!$C$4 -> 376517.02 | E7: =+IQR_results_usd!E7*FXs!$C$5 -> 526994.59 | F7: =+IQR_results_usd!F7*FXs!$C$6 -> 503601.55 | G7: =+IQR_results_usd!G7*FXs!$C$7 -> 690874.17 | H7: =+IQR_results_usd!H7*FXs!$C$8 -> 1102434.7 | I7: =+IQR_results_usd!I7*FXs!$C$9 -> 3042187.7 | J7: =+IQR_results_usd!J7*FXs!$C$10 -> 4129002.5 | K7: =+IQR_results_usd!K7*FXs!$C$11 -> 2497833.1
A8: Total Income & Expenses | B8: =+IQR_results_usd!B8*FXs!$C$2 -> 105363.84 | C8: =+IQR_results_usd!C8*FXs!$C$3 -> -72133.792 | D8: =+IQR_results_usd!D8*FXs!$C$4 -> -7653.73 | E8: =+IQR_results_usd!E8*FXs!$C$5 -> -2785.898 | F8: =+IQR_results_usd!F8*FXs!$C$6 -> 15228.112 | G8: =+IQR_results_usd!G8*FXs!$C$7 -> -150451.34 | H8: =+IQR_results_usd!H8*FXs!$C$8 -> -16279.273 | I8: =+IQR_results_usd!I8*FXs!$C$9 -> 167380.9 | J8: =+IQR_results_usd!J8*FXs!$C$10 -> -65447.218 | K8: =+IQR_results_usd!K8*FXs!$C$11 -> 1111728.1
A9: Total Assets | B9: =+IQR_results_usd!B9*FXs!$C$2 -> 1114172.3 | C9: =+IQR_results_usd!C9*FXs!$C$3 -> 1307053 | D9: =+IQR_results_usd!D9*FXs!$C$4 -> 1510402.8 | E9: =+IQR_results_usd!E9*FXs!$C$5 -> 1892726.6 | F9: =+IQR_results_usd!F9*FXs!$C$6 -> 2481094 | G9: =+IQR_results_usd!G9*FXs!$C$7 -> 2957919.6 | H9: =+IQR_results_usd!H9*FXs!$C$8 -> 3627407 | I9: =+IQR_results_usd!I9*FXs!$C$9 -> 12194665 | J9: =+IQR_results_usd!J9*FXs!$C$10 -> 20254437 | K9: =+IQR_results_usd!K9*FXs!$C$11 -> 30745399
A10: Total Liabs & Net Worth | B10: =+IQR_results_usd!B10*FXs!$C$2 -> 1108046.9 | C10: =+IQR_results_usd!C10*FXs!$C$3 -> 1307053 | D10: =+IQR_results_usd!D10*FXs!$C$4 -> 1510402.8 | E10: =+IQR_results_usd!E10*FXs!$C$5 -> 1892726.6 | F10: =+IQR_results_usd!F10*FXs!$C$6 -> 2481094 | G10: =+IQR_results_usd!G10*FXs!$C$7 -> 2957919.6 | H10: =+IQR_results_usd!H10*FXs!$C$8 -> 3627407 | I10: =+IQR_results_usd!I10*FXs!$C$9 -> 12194665 | J10: =+IQR_results_usd!J10*FXs!$C$10 -> 20254437 | K10: =+IQR_results_usd!K10*FXs!$C$11 -> 30745399
A11: Land | B11: =+IQR_results_usd!B11*FXs!$C$2 -> 14032.667 | C11: =+IQR_results_usd!C11*FXs!$C$3 -> 14032.667 | D11: =+IQR_results_usd!D11*FXs!$C$4 -> 23403.323 | E11: =+IQR_results_usd!E11*FXs!$C$5 -> 33060.353 | F11: =+IQR_results_usd!F11*FXs!$C$6 -> 103852.85 | G11: =+IQR_results_usd!G11*FXs!$C$7 -> 101279.09 | H11: =+IQR_results_usd!H11*FXs!$C$8 -> 98968.693 | I11: =+IQR_results_usd!I11*FXs!$C$9 -> 120278.06 | J11: =+IQR_results_usd!J11*FXs!$C$10 -> 290929.45 | K11: =+IQR_results_usd!K11*FXs!$C$11 -> 448557.67
A12: Buildings | B12: =+IQR_results_usd!B12*FXs!$C$2 -> 833762.12 | C12: =+IQR_results_usd!C12*FXs!$C$3 -> 1043360.1 | D12: =+IQR_results_usd!D12*FXs!$C$4 -> 1260884.4 | E12: =+IQR_results_usd!E12*FXs!$C$5 -> 1617813.9 | F12: =+IQR_results_usd!F12*FXs!$C$6 -> 1804326.9 | G12: =+IQR_results_usd!G12*FXs!$C$7 -> 2078253.5 | H12: =+IQR_results_usd!H12*FXs!$C$8 -> 2557937 | I12: =+IQR_results_usd!I12*FXs!$C$9 -> 7193567.1 | J12: =+IQR_results_usd!J12*FXs!$C$10 -> 13525188 | K12: =+IQR_results_usd!K12*FXs!$C$11 -> 16975662
A13: Leasehold Improvements | B13: =+IQR_results_usd!B13*FXs!$C$2 -> 1403.519 | C13: =+IQR_results_usd!C13*FXs!$C$3 -> 1427.037 | D13: =+IQR_results_usd!D13*FXs!$C$4 -> 2041.371 | E13: =+IQR_results_usd!E13*FXs!$C$5 -> 2721.856 | F13: =+IQR_results_usd!F13*FXs!$C$6 -> 3448.04 | G13: =+IQR_results_usd!G13*FXs!$C$7 -> 3453.29 | H13: =+IQR_results_usd!H13*FXs!$C$8 -> 3511.326 | I13: =+IQR_results_usd!I13*FXs!$C$9 -> 19925.234 | J13: =+IQR_results_usd!J13*FXs!$C$10 -> 25704.472 | K13: =+IQR_results_usd!K13*FXs!$C$11 -> 28709.24
A14: Plant & Equipment | B14: =+IQR_results_usd!B14*FXs!$C$2 -> 20939.671 | C14: =+IQR_results_usd!C14*FXs!$C$3 -> 25333.043 | D14: =+IQR_results_usd!D14*FXs!$C$4 -> 29666.922 | E14: =+IQR_results_usd!E14*FXs!$C$5 -> 34707.234 | F14: =+IQR_results_usd!F14*FXs!$C$6 -> 36676.018 | G14: =+IQR_results_usd!G14*FXs!$C$7 -> 41352.778 | H14: =+IQR_results_usd!H14*FXs!$C$8 -> 49195.082 | I14: =+IQR_results_usd!I14*FXs!$C$9 -> 215053.46 | J14: =+IQR_results_usd!J14*FXs!$C$10 -> 368293.23 | K14: =+IQR_results_usd!K14*FXs!$C$11 -> 432329.51
A15: Furniture & Fixtures | B15: =+IQR_results_usd!B15*FXs!$C$2 -> 119819.36 | C15: =+IQR_results_usd!C15*FXs!$C$3 -> 153420.68 | D15: =+IQR_results_usd!D15*FXs!$C$4 -> 181671.88 | E15: =+IQR_results_usd!E15*FXs!$C$5 -> 206840.7 | F15: =+IQR_results_usd!F15*FXs!$C$6 -> 240029.24 | G15: =+IQR_results_usd!G15*FXs!$C$7 -> 259654.77 | H15: =+IQR_results_usd!H15*FXs!$C$8 -> 304228.85 | I15: =+IQR_results_usd!I15*FXs!$C$9 -> 1555545.8 | J15: =+IQR_results_usd!J15*FXs!$C$10 -> 2211598.6 | K15: =+IQR_results_usd!K15*FXs!$C$11 -> 2915529
A16: Vehicles & Transport Equipment | B16: =+IQR_results_usd!B16*FXs!$C$2 -> 78074.387 | C16: =+IQR_results_usd!C16*FXs!$C$3 -> 78665.806 | D16: =+IQR_results_usd!D16*FXs!$C$4 -> 111033.76 | E16: =+IQR_results_usd!E16*FXs!$C$5 -> 140028.73 | F16: =+IQR_results_usd!F16*FXs!$C$6 -> 158375.26 | G16: =+IQR_results_usd!G16*FXs!$C$7 -> 194663.89 | H16: =+IQR_results_usd!H16*FXs!$C$8 -> 224867.58 | I16: =+IQR_results_usd!I16*FXs!$C$9 -> 696144.92 | J16: =+IQR_results_usd!J16*FXs!$C$10 -> 1084077 | K16: =+IQR_results_usd!K16*FXs!$C$11 -> 952913.3
A17: Other Fixed Assets | B17: =+IQR_results_usd!B17*FXs!$C$2 -> 0 | C17: =+IQR_results_usd!C17*FXs!$C$3 -> 0 | D17: =+IQR_results_usd!D17*FXs!$C$4 -> 0 | E17: =+IQR_results_usd!E17*FXs!$C$5 -> 0 | F17: =+IQR_results_usd!F17*FXs!$C$6 -> 0 | G17: =+IQR_results_usd!G17*FXs!$C$7 -> 0 | H17: =+IQR_results_usd!H17*FXs!$C$8 -> 0 | I17: =+IQR_results_usd!I17*FXs!$C$9 -> 14708.053 | J17: =+IQR_results_usd!J17*FXs!$C$10 -> 35116.507 | K17: =+IQR_results_usd!K17*FXs!$C$11 -> 82636.929
... A225: Minority Interests | B225: =+IQR_results_usd!B225*FXs!$C$2 -> 0 | C225: =+IQR_results_usd!C225*FXs!$C$3 -> 0 | D225: =+IQR_results_usd!D225*FXs!$C$4 -> 0 | E225: =+IQR_results_usd!E225*FXs!$C$5 -> 0 | F225: =+IQR_results_usd!F225*FXs!$C$6 -> 0 | G225: =+IQR_results_usd!G225*FXs!$C$7 -> 0 | H225: =+IQR_results_usd!H225*FXs!$C$8 -> 0 | I225: =+IQR_results_usd!I225*FXs!$C$9 -> 0 | J225: =+IQR_results_usd!J225*FXs!$C$10 -> 0 | K225: =+IQR_results_usd!K225*FXs!$C$11 -> 0

Sheet Sayfa1
B1: 2015 | C1: 2016 | D1: 2017 | E1: 2018 | F1: 2019 | G1: 2020 | H1: 2021 | I1: 2022 | J1: 2023 | K1: 2024 | T1: 0
A2: Periods | B2: 12 | C2: 12 | D2: 12 | E2: 12 | F2: 12 | G2: 12 | H2: 12 | I2: 12 | J2: 12 | K2: 12
A3: Total Non-Current Assets | B3: =+(final_results!B3-Raw_Financials!B3)/Raw_Financials!B3 -> 0 | C3: =+(final_results!C3-Raw_Financials!C3)/Raw_Financials!C3 -> 0 | D3: =+(final_results!D3-Raw_Financials!D3)/Raw_Financials!D3 -> 0 | E3: =+(final_results!E3-Raw_Financials!E3)/Raw_Financials!E3 -> 0 | F3: =+(final_results!F3-Raw_Financials!F3)/Raw_Financials!F3 -> 0 | G3: =+(final_results!G3-Raw_Financials!G3)/Raw_Financials!G3 -> 0 | H3: =+(final_results!H3-Raw_Financials!H3)/Raw_Financials!H3 -> 0 | I3: =+(final_results!I3-Raw_Financials!I3)/Raw_Financials!I3 -> 0 | ... K3: =+(final_results!K3-Raw_Financials!K3)/Raw_Financials!K3 -> 0 | M3: =223*10 -> 2230 | N3: adet veri var
A4: Total Current Assets | B4: =+(final_results!B4-Raw_Financials!B4)/Raw_Financials!B4 -> 0 | C4: =+(final_results!C4-Raw_Financials!C4)/Raw_Financials!C4 -> 0 | D4: =+(final_results!D4-Raw_Financials!D4)/Raw_Financials!D4 -> 0 | E4: =+(final_results!E4-Raw_Financials!E4)/Raw_Financials!E4 -> 0 | F4: =+(final_results!F4-Raw_Financials!F4)/Raw_Financials!F4 -> 0 | G4: =+(final_results!G4-Raw_Financials!G4)/Raw_Financials!G4 -> 0 | H4: =+(final_results!H4-Raw_Financials!H4)/Raw_Financials!H4 -> 0 | I4: =+(final_results!I4-Raw_Financials!I4)/Raw_Financials!I4 -> 0 | ... K4: =+(final_results!K4-Raw_Financials!K4)/Raw_Financials!K4 -> 0 | M4: =COUNTIF(B3:K225, ">"&T1) + COUNTIF(B3:K225, "<"&T1) -> 159 | N4: outlier sayısı (adet)
A5: Total Equity & Reserves | B5: =+(final_results!B5-Raw_Financials!B5)/Raw_Financials!B5 -> 0 | C5: =+(final_results!C5-Raw_Financials!C5)/Raw_Financials!C5 -> 0 | D5: =+(final_results!D5-Raw_Financials!D5)/Raw_Financials!D5 -> 0 | E5: =+(final_results!E5-Raw_Financials!E5)/Raw_Financials!E5 -> 0 | F5: =+(final_results!F5-Raw_Financials!F5)/Raw_Financials!F5 -> 0 | G5: =+(final_results!G5-Raw_Financials!G5)/Raw_Financials!G5 -> 0 | H5: =+(final_results!H5-Raw_Financials!H5)/Raw_Financials!H5 -> 0 | I5: =+(final_results!I5-Raw_Financials!I5)/Raw_Financials!I5 -> 0 | ... K5: =+(final_results!K5-Raw_Financials!K5)/Raw_Financials!K5 -> 0 | M5: =+M4/M3 -> 0.071300448 | N5: outlier (%) (adet)
A6: Total Non-Current Liabilities | B6: =+(final_results!B6-Raw_Financials!B6)/Raw_Financials!B6 -> 0 | C6: =+(final_results!C6-Raw_Financials!C6)/Raw_Financials!C6 -> 0 | D6: =+(final_results!D6-Raw_Financials!D6)/Raw_Financials!D6 -> 0 | E6: =+(final_results!E6-Raw_Financials!E6)/Raw_Financials!E6 -> 0 | F6: =+(final_results!F6-Raw_Financials!F6)/Raw_Financials!F6 -> 0 | G6: =+(final_results!G6-Raw_Financials!G6)/Raw_Financials!G6 -> 0 | H6: =+(final_results!H6-Raw_Financials!H6)/Raw_Financials!H6 -> 0 | I6: =+(final_results!I6-Raw_Financials!I6)/Raw_Financials!I6 -> 0 | ... K6: =+(final_results!K6-Raw_Financials!K6)/Raw_Financials!K6 -> 0
A7: Total Current Liabilities | B7: =+(final_results!B7-Raw_Financials!B7)/Raw_Financials!B7 -> 0 | C7: =+(final_results!C7-Raw_Financials!C7)/Raw_Financials!C7 -> 0 | D7: =+(final_results!D7-Raw_Financials!D7)/Raw_Financials!D7 -> 0 | E7: =+(final_results!E7-Raw_Financials!E7)/Raw_Financials!E7 -> 0 | F7: =+(final_results!F7-Raw_Financials!F7)/Raw_Financials!F7 -> 0 | G7: =+(final_results!G7-Raw_Financials!G7)/Raw_Financials!G7 -> 0 | H7: =+(final_results!H7-Raw_Financials!H7)/Raw_Financials!H7 -> 0 | I7: =+(final_results!I7-Raw_Financials!I7)/Raw_Financials!I7 -> -0.026235986 | ... K7: =+(final_results!K7-Raw_Financials!K7)/Raw_Financials!K7 -> 0
A8: Total Income & Expenses | B8: =+(final_results!B8-Raw_Financials!B8)/Raw_Financials!B8 -> -0.62937422 | C8: =+(final_results!C8-Raw_Financials!C8)/Raw_Financials!C8 -> 0 | D8: =+(final_results!D8-Raw_Financials!D8)/Raw_Financials!D8 -> 0 | E8: =+(final_results!E8-Raw_Financials!E8)/Raw_Financials!E8 -> 0 | F8: =+(final_results!F8-Raw_Financials!F8)/Raw_Financials!F8 -> 1.1944944e-16 | G8: =+(final_results!G8-Raw_Financials!G8)/Raw_Financials!G8 -> 0 | H8: =+(final_results!H8-Raw_Financials!H8)/Raw_Financials!H8 -> 0 | I8: =+(final_results!I8-Raw_Financials!I8)/Raw_Financials!I8 -> 0 | ... K8: =+(final_results!K8-Raw_Financials!K8)/Raw_Financials!K8 -> 0
A9: Total Assets | B9: =+(final_results!B9-Raw_Financials!B9)/Raw_Financials!B9 -> 0 | C9: =+(final_results!C9-Raw_Financials!C9)/Raw_Financials!C9 -> 0 | D9: =+(final_results!D9-Raw_Financials!D9)/Raw_Financials!D9 -> 0 | E9: =+(final_results!E9-Raw_Financials!E9)/Raw_Financials!E9 -> 0 | F9: =+(final_results!F9-Raw_Financials!F9)/Raw_Financials!F9 -> 0 | G9: =+(final_results!G9-Raw_Financials!G9)/Raw_Financials!G9 -> 0 | H9: =+(final_results!H9-Raw_Financials!H9)/Raw_Financials!H9 -> -1.2837305e-16 | I9: =+(final_results!I9-Raw_Financials!I9)/Raw_Financials!I9 -> 1.5274262e-16 | ... K9: =+(final_results!K9-Raw_Financials!K9)/Raw_Financials!K9 -> 0
A10: Total Liabs & Net Worth | B10: =+(final_results!B10-Raw_Financials!B10)/Raw_Financials!B10 -> 0 | C10: =+(final_results!C10-Raw_Financials!C10)/Raw_Financials!C10 -> 0 | D10: =+(final_results!D10-Raw_Financials!D10)/Raw_Financials!D10 -> 0 | E10: =+(final_results!E10-Raw_Financials!E10)/Raw_Financials!E10 -> -1.2301335e-16 | F10: =+(final_results!F10-Raw_Financials!F10)/Raw_Financials!F10 -> 0 | G10: =+(final_results!G10-Raw_Financials!G10)/Raw_Financials!G10 -> 0 | H10: =+(final_results!H10-Raw_Financials!H10)/Raw_Financials!H10 -> 1.2837305e-16 | I10: =+(final_results!I10-Raw_Financials!I10)/Raw_Financials!I10 -> 0 | ... K10: =+(final_results!K10-Raw_Financials!K10)/Raw_Financials!K10 -> 0
A11: Land | B11: =+(final_results!B11-Raw_Financials!B11)/Raw_Financials!B11 -> 0 | C11: =+(final_results!C11-Raw_Financials!C11)/Raw_Financials!C11 -> 0 | D11: =+(final_results!D11-Raw_Financials!D11)/Raw_Financials!D11 -> 0 | E11: =+(final_results!E11-Raw_Financials!E11)/Raw_Financials!E11 -> 0 | F11: =+(final_results!F11-Raw_Financials!F11)/Raw_Financials!F11 -> -1.4012052e-16 | G11: =+(final_results!G11-Raw_Financials!G11)/Raw_Financials!G11 -> 0 | H11: =+(final_results!H11-Raw_Financials!H11)/Raw_Financials!H11 -> 0 | I11: =+(final_results!I11-Raw_Financials!I11)/Raw_Financials!I11 -> 1.2098561e-16 | ... K11: =+(final_results!K11-Raw_Financials!K11)/Raw_Financials!K11 -> 0
A12: Buildings | B12: =+(final_results!B12-Raw_Financials!B12)/Raw_Financials!B12 -> 0 | C12: =+(final_results!C12-Raw_Financials!C12)/Raw_Financials!C12 -> 0 | D12: =+(final_results!D12-Raw_Financials!D12)/Raw_Financials!D12 -> 0 | E12: =+(final_results!E12-Raw_Financials!E12)/Raw_Financials!E12 -> 0 | F12: =+(final_results!F12-Raw_Financials!F12)/Raw_Financials!F12 -> 0 | G12: =+(final_results!G12-Raw_Financials!G12)/Raw_Financials!G12 -> -1.1203188e-16 | H12: =+(final_results!H12-Raw_Financials!H12)/Raw_Financials!H12 -> 0 | I12: =+(final_results!I12-Raw_Financials!I12)/Raw_Financials!I12 -> 0 | ... K12: =+(final_results!K12-Raw_Financials!K12)/Raw_Financials!K12 -> 0
A13: Leasehold Improvements | B13: =+(final_results!B13-Raw_Financials!B13)/Raw_Financials!B13 -> 0 | C13: =+(final_results!C13-Raw_Financials!C13)/Raw_Financials!C13 -> 0 | D13: =+(final_results!D13-Raw_Financials!D13)/Raw_Financials!D13 -> 0 | E13: =+(final_results!E13-Raw_Financials!E13)/Raw_Financials!E13 -> 0 | F13: =+(final_results!F13-Raw_Financials!F13)/Raw_Financials!F13 -> 0 | G13: =+(final_results!G13-Raw_Financials!G13)/Raw_Financials!G13 -> 0 | H13: =+(final_results!H13-Raw_Financials!H13)/Raw_Financials!H13 -> -1.2950872e-16 | I13: =+(final_results!I13-Raw_Financials!I13)/Raw_Financials!I13 -> 0 | ... K13: =+(final_results!K13-Raw_Financials!K13)/Raw_Financials!K13 -> 0
A14: Plant & Equipment | B14: =+(final_results!B14-Raw_Financials!B14)/Raw_Financials!B14 -> 0 | C14: =+(final_results!C14-Raw_Financials!C14)/Raw_Financials!C14 -> 0 | D14: =+(final_results!D14-Raw_Financials!D14)/Raw_Financials!D14 -> 0 | E14: =+(final_results!E14-Raw_Financials!E14)/Raw_Financials!E14 -> 0 | F14: =+(final_results!F14-Raw_Financials!F14)/Raw_Financials!F14 -> 0 | G14: =+(final_results!G14-Raw_Financials!G14)/Raw_Financials!G14 -> 0 | H14: =+(final_results!H14-Raw_Financials!H14)/Raw_Financials!H14 -> 0 | I14: =+(final_results!I14-Raw_Financials!I14)/Raw_Financials!I14 -> 0 | ... K14: =+(final_results!K14-Raw_Financials!K14)/Raw_Financials!K14 -> 0
A15: Furniture & Fixtures | B15: =+(final_results!B15-Raw_Financials!B15)/Raw_Financials!B15 -> -1.2144878e-16 | C15: =+(final_results!C15-Raw_Financials!C15)/Raw_Financials!C15 -> 0 | D15: =+(final_results!D15-Raw_Financials!D15)/Raw_Financials!D15 -> 0 | E15: =+(final_results!E15-Raw_Financials!E15)/Raw_Financials!E15 -> 0 | F15: =+(final_results!F15-Raw_Financials!F15)/Raw_Financials!F15 -> 0 | G15: =+(final_results!G15-Raw_Financials!G15)/Raw_Financials!G15 -> -1.1208664e-16 | H15: =+(final_results!H15-Raw_Financials!H15)/Raw_Financials!H15 -> 0 | I15: =+(final_results!I15-Raw_Financials!I15)/Raw_Financials!I15 -> 0 | ... K15: =+(final_results!K15-Raw_Financials!K15)/Raw_Financials!K15 -> 0
A16: Vehicles & Transport Equipment | B16: =+(final_results!B16-Raw_Financials!B16)/Raw_Financials!B16 -> 0 | C16: =+(final_results!C16-Raw_Financials!C16)/Raw_Financials!C16 -> 0 | D16: =+(final_results!D16-Raw_Financials!D16)/Raw_Financials!D16 -> 0 | E16: =+(final_results!E16-Raw_Financials!E16)/Raw_Financials!E16 -> 0 | F16: =+(final_results!F16-Raw_Financials!F16)/Raw_Financials!F16 -> 0 | G16: =+(final_results!G16-Raw_Financials!G16)/Raw_Financials!G16 -> 0 | H16: =+(final_results!H16-Raw_Financials!H16)/Raw_Financials!H16 -> 0.077926942 | I16: =+(final_results!I16-Raw_Financials!I16)/Raw_Financials!I16 -> -0.23155553 | ... K16: =+(final_results!K16-Raw_Financials!K16)/Raw_Financials!K16 -> 0
A17: Other Fixed Assets | B17: =+(final_results!B17-Raw_Financials!B17)/Raw_Financials!B17 -> #DIV/0! | C17: =+(final_results!C17-Raw_Financials!C17)/Raw_Financials!C17 -> #DIV/0! | D17: =+(final_results!D17-Raw_Financials!D17)/Raw_Financials!D17 -> #DIV/0! | E17: =+(final_results!E17-Raw_Financials!E17)/Raw_Financials!E17 -> #DIV/0! | F17: =+(final_results!F17-Raw_Financials!F17)/Raw_Financials!F17 -> #DIV/0! | G17: =+(final_results!G17-Raw_Financials!G17)/Raw_Financials!G17 -> #DIV/0! | H17: =+(final_results!H17-Raw_Financials!H17)/Raw_Financials!H17 -> #DIV/0! | I17: =+(final_results!I17-Raw_Financials!I17)/Raw_Financials!I17 -> 0 | ... K17: =+(final_results!K17-Raw_Financials!K17)/Raw_Financials!K17 -> -0.47336393
... A225: Minority Interests | B225: =+(final_results!B225-Raw_Financials!B225)/Raw_Financials!B225 -> #DIV/0! | C225: =+(final_results!C225-Raw_Financials!C225)/Raw_Financials!C225 -> #DIV/0! | D225: =+(final_results!D225-Raw_Financials!D225)/Raw_Financials!D225 -> #DIV/0! | E225: =+(final_results!E225-Raw_Financials!E225)/Raw_Financials!E225 -> #DIV/0! | F225: =+(final_results!F225-Raw_Financials!F225)/Raw_Financials!F225 -> #DIV/0! | G225: =+(final_results!G225-Raw_Financials!G225)/Raw_Financials!G225 -> #DIV/0! | H225: =+(final_results!H225-Raw_Financials!H225)/Raw_Financials!H225 -> #DIV/0! | I225: =+(final_results!I225-Raw_Financials!I225)/Raw_Financials!I225 -> #DIV/0! | ... K225: =+(final_results!K225-Raw_Financials!K225)/Raw_Financials!K225 -> #DIV/0!

Sheet Sayfa2
B1: 2015 | C1: 2016 | D1: 2017 | E1: 2018 | F1: 2019 | G1: 2020 | H1: 2021 | I1: 2022 | J1: 2023 | K1: 2024
A2: Periods | B2: 12 | C2: 12 | D2: 12 | E2: 12 | F2: 12 | G2: 12 | H2: 12 | I2: 12 | J2: 12 | K2: 12
A3: Total Non-Current Assets | B3: =+final_results!B3-Raw_Financials!B3 -> 0 | C3: =+final_results!C3-Raw_Financials!C3 -> 0 | D3: =+final_results!D3-Raw_Financials!D3 -> 0 | E3: =+final_results!E3-Raw_Financials!E3 -> 0 | F3: =+final_results!F3-Raw_Financials!F3 -> 0 | G3: =+final_results!G3-Raw_Financials!G3 -> 0 | H3: =+final_results!H3-Raw_Financials!H3 -> 0 | I3: =+final_results!I3-Raw_Financials!I3 -> 0 | ... K3: =+final_results!K3-Raw_Financials!K3 -> 0 | M3: =+SUM(Raw_Financials!B3:K225) -> 8.0116304e+08 | N3: tüm verilerin toplamı
A4: Total Current Assets | B4: =+final_results!B4-Raw_Financials!B4 -> 0 | C4: =+final_results!C4-Raw_Financials!C4 -> 0 | D4: =+final_results!D4-Raw_Financials!D4 -> 0 | E4: =+final_results!E4-Raw_Financials!E4 -> 0 | F4: =+final_results!F4-Raw_Financials!F4 -> 0 | G4: =+final_results!G4-Raw_Financials!G4 -> 0 | H4: =+final_results!H4-Raw_Financials!H4 -> 0 | I4: =+final_results!I4-Raw_Financials!I4 -> 0 | ... K4: =+final_results!K4-Raw_Financials!K4 -> 0 | M4: =+SUM(B3:K225) -> -30544087 | N4: outlier olan tutarların toplamı
A5: Total Equity & Reserves | B5: =+final_results!B5-Raw_Financials!B5 -> 0 | C5: =+final_results!C5-Raw_Financials!C5 -> 0 | D5: =+final_results!D5-Raw_Financials!D5 -> 0 | E5: =+final_results!E5-Raw_Financials!E5 -> 0 | F5: =+final_results!F5-Raw_Financials!F5 -> 0 | G5: =+final_results!G5-Raw_Financials!G5 -> 0 | H5: =+final_results!H5-Raw_Financials!H5 -> 0 | I5: =+final_results!I5-Raw_Financials!I5 -> 0 | ... K5: =+final_results!K5-Raw_Financials!K5 -> 0 | M5: =ABS(M4)/M3 -> 0.038124684 | N5: Parasal Oran
A6: Total Non-Current Liabilities | B6: =+final_results!B6-Raw_Financials!B6 -> 0 | C6: =+final_results!C6-Raw_Financials!C6 -> 0 | D6: =+final_results!D6-Raw_Financials!D6 -> 0 | E6: =+final_results!E6-Raw_Financials!E6 -> 0 | F6: =+final_results!F6-Raw_Financials!F6 -> 0 | G6: =+final_results!G6-Raw_Financials!G6 -> 0 | H6: =+final_results!H6-Raw_Financials!H6 -> 0 | I6: =+final_results!I6-Raw_Financials!I6 -> 0 | ... K6: =+final_results!K6-Raw_Financials!K6 -> 0
A7: Total Current Liabilities | B7: =+final_results!B7-Raw_Financials!B7 -> 0 | C7: =+final_results!C7-Raw_Financials!C7 -> 0 | D7: =+final_results!D7-Raw_Financials!D7 -> 0 | E7: =+final_results!E7-Raw_Financials!E7 -> 0 | F7: =+final_results!F7-Raw_Financials!F7 -> 0 | G7: =+final_results!G7-Raw_Financials!G7 -> 0 | H7: =+final_results!H7-Raw_Financials!H7 -> 0 | I7: =+final_results!I7-Raw_Financials!I7 -> -81965.233 | ... K7: =+final_results!K7-Raw_Financials!K7 -> 0
A8: Total Income & Expenses | B8: =+final_results!B8-Raw_Financials!B8 -> -178922.48 | C8: =+final_results!C8-Raw_Financials!C8 -> 0 | D8: =+final_results!D8-Raw_Financials!D8 -> 0 | E8: =+final_results!E8-Raw_Financials!E8 -> 0 | F8: =+final_results!F8-Raw_Financials!F8 -> 0 | G8: =+final_results!G8-Raw_Financials!G8 -> 0 | H8: =+final_results!H8-Raw_Financials!H8 -> 0 | I8: =+final_results!I8-Raw_Financials!I8 -> 0 | ... K8: =+final_results!K8-Raw_Financials!K8 -> 0
A9: Total Assets | B9: =+final_results!B9-Raw_Financials!B9 -> 0 | C9: =+final_results!C9-Raw_Financials!C9 -> 0 | D9: =+final_results!D9-Raw_Financials!D9 -> 0 | E9: =+final_results!E9-Raw_Financials!E9 -> 0 | F9: =+final_results!F9-Raw_Financials!F9 -> 0 | G9: =+final_results!G9-Raw_Financials!G9 -> 0 | H9: =+final_results!H9-Raw_Financials!H9 -> 0 | I9: =+final_results!I9-Raw_Financials!I9 -> 0 | ... K9: =+final_results!K9-Raw_Financials!K9 -> 0 | M9: "Analiz sonucunda verinin %7.1'i (adet bazında) aykırı bulunmuş, ancak bu aykırı değerlerin toplam parasal hacme etkisi (Materiality) sadece %3.8 ile sınırlı kalmıştır. Bu da uygulanan Winsorization yönteminin finansal tablonun ana gövdesini bozmadan, sadece uçlardaki gürültüyü temizlediğini göstermektedir."
A10: Total Liabs & Net Worth | B10: =+final_results!B10-Raw_Financials!B10 -> 0 | C10: =+final_results!C10-Raw_Financials!C10 -> 0 | D10: =+final_results!D10-Raw_Financials!D10 -> 0 | E10: =+final_results!E10-Raw_Financials!E10 -> 0 | F10: =+final_results!F10-Raw_Financials!F10 -> 0 | G10: =+final_results!G10-Raw_Financials!G10 -> 0 | H10: =+final_results!H10-Raw_Financials!H10 -> 0 | I10: =+final_results!I10-Raw_Financials!I10 -> 0 | ... K10: =+final_results!K10-Raw_Financials!K10 -> 0
A11: Land | B11: =+final_results!B11-Raw_Financials!B11 -> 0 | C11: =+final_results!C11-Raw_Financials!C11 -> 0 | D11: =+final_results!D11-Raw_Financials!D11 -> 0 | E11: =+final_results!E11-Raw_Financials!E11 -> 0 | F11: =+final_results!F11-Raw_Financials!F11 -> 0 | G11: =+final_results!G11-Raw_Financials!G11 -> 0 | H11: =+final_results!H11-Raw_Financials!H11 -> 0 | I11: =+final_results!I11-Raw_Financials!I11 -> 0 | ... K11: =+final_results!K11-Raw_Financials!K11 -> 0
A12: Buildings | B12: =+final_results!B12-Raw_Financials!B12 -> 0 | C12: =+final_results!C12-Raw_Financials!C12 -> 0 | D12: =+final_results!D12-Raw_Financials!D12 -> 0 | E12: =+final_results!E12-Raw_Financials!E12 -> 0 | F12: =+final_results!F12-Raw_Financials!F12 -> 0 | G12: =+final_results!G12-Raw_Financials!G12 -> 0 | H12: =+final_results!H12-Raw_Financials!H12 -> 0 | I12: =+final_results!I12-Raw_Financials!I12 -> 0 | ... K12: =+final_results!K12-Raw_Financials!K12 -> 0
A13: Leasehold Improvements | B13: =+final_results!B13-Raw_Financials!B13 -> 0 | C13: =+final_results!C13-Raw_Financials!C13 -> 0 | D13: =+final_results!D13-Raw_Financials!D13 -> 0 | E13: =+final_results!E13-Raw_Financials!E13 -> 0 | F13: =+final_results!F13-Raw_Financials!F13 -> 0 | G13: =+final_results!G13-Raw_Financials!G13 -> 0 | H13: =+final_results!H13-Raw_Financials!H13 -> 0 | I13: =+final_results!I13-Raw_Financials!I13 -> 0 | ... K13: =+final_results!K13-Raw_Financials!K13 -> 0
A14: Plant & Equipment | B14: =+final_results!B14-Raw_Financials!B14 -> 0 | C14: =+final_results!C14-Raw_Financials!C14 -> 0 | D14: =+final_results!D14-Raw_Financials!D14 -> 0 | E14: =+final_results!E14-Raw_Financials!E14 -> 0 | F14: =+final_results!F14-Raw_Financials!F14 -> 0 | G14: =+final_results!G14-Raw_Financials!G14 -> 0 | H14: =+final_results!H14-Raw_Financials!H14 -> 0 | I14: =+final_results!I14-Raw_Financials!I14 -> 0 | ... K14: =+final_results!K14-Raw_Financials!K14 -> 0
A15: Furniture & Fixtures | B15: =+final_results!B15-Raw_Financials!B15 -> 0 | C15: =+final_results!C15-Raw_Financials!C15 -> 0 | D15: =+final_results!D15-Raw_Financials!D15 -> 0 | E15: =+final_results!E15-Raw_Financials!E15 -> 0 | F15: =+final_results!F15-Raw_Financials!F15 -> 0 | G15: =+final_results!G15-Raw_Financials!G15 -> 0 | H15: =+final_results!H15-Raw_Financials!H15 -> 0 | I15: =+final_results!I15-Raw_Financials!I15 -> 0 | ... K15: =+final_results!K15-Raw_Financials!K15 -> 0
A16: Vehicles & Transport Equipment | B16: =+final_results!B16-Raw_Financials!B16 -> 0 | C16: =+final_results!C16-Raw_Financials!C16 -> 0 | D16: =+final_results!D16-Raw_Financials!D16 -> 0 | E16: =+final_results!E16-Raw_Financials!E16 -> 0 | F16: =+final_results!F16-Raw_Financials!F16 -> 0 | G16: =+final_results!G16-Raw_Financials!G16 -> 0 | H16: =+final_results!H16-Raw_Financials!H16 -> 16256.429 | I16: =+final_results!I16-Raw_Financials!I16 -> -209769.49 | ... K16: =+final_results!K16-Raw_Financials!K16 -> 0
A17: Other Fixed Assets | B17: =+final_results!B17-Raw_Financials!B17 -> 0 | C17: =+final_results!C17-Raw_Financials!C17 -> 0 | D17: =+final_results!D17-Raw_Financials!D17 -> 0 | E17: =+final_results!E17-Raw_Financials!E17 -> 0 | F17: =+final_results!F17-Raw_Financials!F17 -> 0 | G17: =+final_results!G17-Raw_Financials!G17 -> 0 | H17: =+final_results!H17-Raw_Financials!H17 -> 0 | I17: =+final_results!I17-Raw_Financials!I17 -> 0 | ... K17: =+final_results!K17-Raw_Financials!K17 -> -74277.748
A18: Construction in Progress | B18: =+final_results!B18-Raw_Financials!B18 -> 0 | C18: =+final_results!C18-Raw_Financials!C18 -> 0 | D18: =+final_results!D18-Raw_Financials!D18 -> 0 | E18: =+final_results!E18-Raw_Financials!E18 -> 0 | F18: =+final_results!F18-Raw_Financials!F18 -> 0 | G18: =+final_results!G18-Raw_Financials!G18 -> 0 | H18: =+final_results!H18-Raw_Financials!H18 -> 0 | I18: =+final_results!I18-Raw_Financials!I18 -> 0 | ... K18: =+final_results!K18-Raw_Financials!K18 -> 0
A19: Property Development Investments | B19: =+final_results!B19-Raw_Financials!B19 -> 0 | C19: =+final_results!C19-Raw_Financials!C19 -> 0 | D19: =+final_results!D19-Raw_Financials!D19 -> 0 | E19: =+final_results!E19-Raw_Financials!E19 -> 0 | F19: =+final_results!F19-Raw_Financials!F19 -> 0 | G19: =+final_results!G19-Raw_Financials!G19 -> 0 | H19: =+final_results!H19-Raw_Financials!H19 -> 0 | I19: =+final_results!I19-Raw_Financials!I19 -> 0 | ... K19: =+final_results!K19-Raw_Financials!K19 -> 0
A20: Gross Fixed Assets | B20: =+final_results!B20-Raw_Financials!B20 -> 0 | C20: =+final_results!C20-Raw_Financials!C20 -> 0 | D20: =+final_results!D20-Raw_Financials!D20 -> 0 | E20: =+final_results!E20-Raw_Financials!E20 -> 0 | F20: =+final_results!F20-Raw_Financials!F20 -> 0 | G20: =+final_results!G20-Raw_Financials!G20 -> 0 | H20: =+final_results!H20-Raw_Financials!H20 -> 0 | I20: =+final_results!I20-Raw_Financials!I20 -> 0 | ... K20: =+final_results!K20-Raw_Financials!K20 -> 0
A21: Accum Deprec & Impairment (-) | B21: =+final_results!B21-Raw_Financials!B21 -> 0 | C21: =+final_results!C21-Raw_Financials!C21 -> 0 | D21: =+final_results!D21-Raw_Financials!D21 -> 0 | E21: =+final_results!E21-Raw_Financials!E21 -> 0 | F21: =+final_results!F21-Raw_Financials!F21 -> 0 | G21: =+final_results!G21-Raw_Financials!G21 -> 0 | H21: =+final_results!H21-Raw_Financials!H21 -> 0 | I21: =+final_results!I21-Raw_Financials!I21 -> 0 | ... K21: =+final_results!K21-Raw_Financials!K21 -> 0
... A26: Patents | B26: =+final_results!B26-Raw_Financials!B26 -> 0 | C26: =+final_results!C26-Raw_Financials!C26 -> 0 | D26: =+final_results!D26-Raw_Financials!D26 -> 0 | E26: =+final_results!E26-Raw_Financials!E26 -> 0 | F26: =+final_results!F26-Raw_Financials!F26 -> 0 | G26: =+final_results!G26-Raw_Financials!G26 -> 0 | H26: =+final_results!H26-Raw_Financials!H26 -> 0 | I26: =+final_results!I26-Raw_Financials!I26 -> 0 | ... K26: =+final_results!K26-Raw_Financials!K26 -> 0
A27: Start-Up Capitalized Expenses | B27: =+final_results!B27-Raw_Financials!B27 -> 0 | C27: =+final_results!C27-Raw_Financials!C27 -> 0 | D27: =+final_results!D27-Raw_Financials!D27 -> 0 | E27: =+final_results!E27-Raw_Financials!E27 -> 0 | F27: =+final_results!F27-Raw_Financials!F27 -> 0 | G27: =+final_results!G27-Raw_Financials!G27 -> 0 | H27: =+final_results!H27-Raw_Financials!H27 -> 0 | I27: =+final_results!I27-Raw_Financials!I27 -> 0 | ... K27: =+final_results!K27-Raw_Financials!K27 -> 0 | M27: Buna literatürde "Currency Adjustment for Outlier Detection" (Döviz Ayarlamalı Aykırı Değer Tespiti) denir.
A28: R&D Capitalized Expenses | B28: =+final_results!B28-Raw_Financials!B28 -> 0 | C28: =+final_results!C28-Raw_Financials!C28 -> 0 | D28: =+final_results!D28-Raw_Financials!D28 -> 0 | E28: =+final_results!E28-Raw_Financials!E28 -> 0 | F28: =+final_results!F28-Raw_Financials!F28 -> 0 | G28: =+final_results!G28-Raw_Financials!G28 -> 0 | H28: =+final_results!H28-Raw_Financials!H28 -> 0 | I28: =+final_results!I28-Raw_Financials!I28 -> 0 | ... K28: =+final_results!K28-Raw_Financials!K28 -> 0
A29: Leasings | B29: =+final_results!B29-Raw_Financials!B29 -> 0 | C29: =+final_results!C29-Raw_Financials!C29 -> 0 | D29: =+final_results!D29-Raw_Financials!D29 -> 0 | E29: =+final_results!E29-Raw_Financials!E29 -> 0 | F29: =+final_results!F29-Raw_Financials!F29 -> 0 | G29: =+final_results!G29-Raw_Financials!G29 -> 0 | H29: =+final_results!H29-Raw_Financials!H29 -> 0 | I29: =+final_results!I29-Raw_Financials!I29 -> 0 | ... K29: =+final_results!K29-Raw_Financials!K29 -> 0
A30: Other Intangible Assets | B30: =+final_results!B30-Raw_Financials!B30 -> 0 | C30: =+final_results!C30-Raw_Financials!C30 -> 0 | D30: =+final_results!D30-Raw_Financials!D30 -> 0 | E30: =+final_results!E30-Raw_Financials!E30 -> 0 | F30: =+final_results!F30-Raw_Financials!F30 -> 0 | G30: =+final_results!G30-Raw_Financials!G30 -> 0 | H30: =+final_results!H30-Raw_Financials!H30 -> 0 | I30: =+final_results!I30-Raw_Financials!I30 -> 0 | ... K30: =+final_results!K30-Raw_Financials!K30 -> 0
A31: Accum Intgbl Assets Amort(-) | B31: =+final_results!B31-Raw_Financials!B31 -> 0 | C31: =+final_results!C31-Raw_Financials!C31 -> 0 | D31: =+final_results!D31-Raw_Financials!D31 -> 0 | E31: =+final_results!E31-Raw_Financials!E31 -> 0 | F31: =+final_results!F31-Raw_Financials!F31 -> 0 | G31: =+final_results!G31-Raw_Financials!G31 -> 0 | H31: =+final_results!H31-Raw_Financials!H31 -> 0 | I31: =+final_results!I31-Raw_Financials!I31 -> 0 | ... K31: =+final_results!K31-Raw_Financials!K31 -> 0
A32: Net Intangibles | B32: =+final_results!B32-Raw_Financials!B32 -> 0 | C32: =+final_results!C32-Raw_Financials!C32 -> 0 | D32: =+final_results!D32-Raw_Financials!D32 -> 0 | E32: =+final_results!E32-Raw_Financials!E32 -> 0 | F32: =+final_results!F32-Raw_Financials!F32 -> 0 | G32: =+final_results!G32-Raw_Financials!G32 -> 0 | H32: =+final_results!H32-Raw_Financials!H32 -> 0 | I32: =+final_results!I32-Raw_Financials!I32 -> 0 | ... K32: =+final_results!K32-Raw_Financials!K32 -> 0
A33: Investments in Group Companies and LT Associates | B33: =+final_results!B33-Raw_Financials!B33 -> 0 | C33: =+final_results!C33-Raw_Financials!C33 -> 0 | D33: =+final_results!D33-Raw_Financials!D33 -> 0 | E33: =+final_results!E33-Raw_Financials!E33 -> 0 | F33: =+final_results!F33-Raw_Financials!F33 -> 0 | G33: =+final_results!G33-Raw_Financials!G33 -> 0 | H33: =+final_results!H33-Raw_Financials!H33 -> 0 | I33: =+final_results!I33-Raw_Financials!I33 -> 0 | ... K33: =+final_results!K33-Raw_Financials!K33 -> -232655.81
A34: Investments in Associates | B34: =+final_results!B34-Raw_Financials!B34 -> -499.623 | C34: =+final_results!C34-Raw_Financials!C34 -> -11206.319 | D34: =+final_results!D34-Raw_Financials!D34 -> 0 | E34: =+final_results!E34-Raw_Financials!E34 -> 0 | F34: =+final_results!F34-Raw_Financials!F34 -> 0 | G34: =+final_results!G34-Raw_Financials!G34 -> 0 | H34: =+final_results!H34-Raw_Financials!H34 -> 0 | I34: =+final_results!I34-Raw_Financials!I34 -> 0 | ... K34: =+final_results!K34-Raw_Financials!K34 -> 0
A35: Invest in JVs & Partnerships | B35: =+final_results!B35-Raw_Financials!B35 -> 0 | C35: =+final_results!C35-Raw_Financials!C35 -> 0 | D35: =+final_results!D35-Raw_Financials!D35 -> 0 | E35: =+final_results!E35-Raw_Financials!E35 -> 0 | F35: =+final_results!F35-Raw_Financials!F35 -> 0 | G35: =+final_results!G35-Raw_Financials!G35 -> 0 | H35: =+final_results!H35-Raw_Financials!H35 -> 0 | I35: =+final_results!I35-Raw_Financials!I35 -> 0 | ... K35: =+final_results!K35-Raw_Financials!K35 -> 0
A36: Due from Related Parties(LTP) | B36: =+final_results!B36-Raw_Financials!B36 -> -13057.348 | C36: =+final_results!C36-Raw_Financials!C36 -> -1874.545 | D36: =+final_results!D36-Raw_Financials!D36 -> 0 | E36: =+final_results!E36-Raw_Financials!E36 -> 0 | F36: =+final_results!F36-Raw_Financials!F36 -> 0 | G36: =+final_results!G36-Raw_Financials!G36 -> 0 | H36: =+final_results!H36-Raw_Financials!H36 -> 0 | I36: =+final_results!I36-Raw_Financials!I36 -> 0 | ... K36: =+final_results!K36-Raw_Financials!K36 -> 0
A37: Due from S'holder(LTP) | B37: =+final_results!B37-Raw_Financials!B37 -> 0 | C37: =+final_results!C37-Raw_Financials!C37 -> -518.78276 | D37: =+final_results!D37-Raw_Financials!D37 -> 0 | E37: =+final_results!E37-Raw_Financials!E37 -> 0 | F37: =+final_results!F37-Raw_Financials!F37 -> 0 | G37: =+final_results!G37-Raw_Financials!G37 -> 0 | H37: =+final_results!H37-Raw_Financials!H37 -> 0 | I37: =+final_results!I37-Raw_Financials!I37 -> 0 | ... K37: =+final_results!K37-Raw_Financials!K37 -> 0
A38: Secur & Other Fincl Assets(LTP) | B38: =+final_results!B38-Raw_Financials!B38 -> 0 | C38: =+final_results!C38-Raw_Financials!C38 -> 0 | D38: =+final_results!D38-Raw_Financials!D38 -> 0 | E38: =+final_results!E38-Raw_Financials!E38 -> 0 | F38: =+final_results!F38-Raw_Financials!F38 -> 0 | G38: =+final_results!G38-Raw_Financials!G38 -> 0 | H38: =+final_results!H38-Raw_Financials!H38 -> 0 | I38: =+final_results!I38-Raw_Financials!I38 -> 0 | ... K38: =+final_results!K38-Raw_Financials!K38 -> 0
A39: Accum Deprec of Financial Assets(-) | B39: =+final_results!B39-Raw_Financials!B39 -> 0 | C39: =+final_results!C39-Raw_Financials!C39 -> 0 | D39: =+final_results!D39-Raw_Financials!D39 -> 0 | E39: =+final_results!E39-Raw_Financials!E39 -> 0 | F39: =+final_results!F39-Raw_Financials!F39 -> 0 | G39: =+final_results!G39-Raw_Financials!G39 -> 0 | H39: =+final_results!H39-Raw_Financials!H39 -> 0 | I39: =+final_results!I39-Raw_Financials!I39 -> 0 | ... K39: =+final_results!K39-Raw_Financials!K39 -> 0
A40: Deriv & Hedg Assets(LTP) | B40: =+final_results!B40-Raw_Financials!B40 -> 0 | C40: =+final_results!C40-Raw_Financials!C40 -> 0 | D40: =+final_results!D40-Raw_Financials!D40 -> 0 | E40: =+final_results!E40-Raw_Financials!E40 -> 0 | F40: =+final_results!F40-Raw_Financials!F40 -> 0 | G40: =+final_results!G40-Raw_Financials!G40 -> 0 | H40: =+final_results!H40-Raw_Financials!H40 -> 0 | I40: =+final_results!I40-Raw_Financials!I40 -> 0 | ... K40: =+final_results!K40-Raw_Financials!K40 -> 0 | M40: Tezin "Metodoloji" Kısmına Yazılacak Metin
A41: Rtrmnt Plan Actuarial Surplus | B41: =+final_results!B41-Raw_Financials!B41 -> 0 | C41: =+final_results!C41-Raw_Financials!C41 -> 0 | D41: =+final_results!D41-Raw_Financials!D41 -> 0 | E41: =+final_results!E41-Raw_Financials!E41 -> 0 | F41: =+final_results!F41-Raw_Financials!F41 -> 0 | G41: =+final_results!G41-Raw_Financials!G41 -> 0 | H41: =+final_results!H41-Raw_Financials!H41 -> 0 | I41: =+final_results!I41-Raw_Financials!I41 -> 0 | ... K41: =+final_results!K41-Raw_Financials!K41 -> 0
A42: Other Non-Current Assets | B42: =+final_results!B42-Raw_Financials!B42 -> 0 | C42: =+final_results!C42-Raw_Financials!C42 -> 0 | D42: =+final_results!D42-Raw_Financials!D42 -> 0 | E42: =+final_results!E42-Raw_Financials!E42 -> 0 | F42: =+final_results!F42-Raw_Financials!F42 -> -93.813961 | G42: =+final_results!G42-Raw_Financials!G42 -> 0 | H42: =+final_results!H42-Raw_Financials!H42 -> -0.94673469 | I42: =+final_results!I42-Raw_Financials!I42 -> 0 | ... K42: =+final_results!K42-Raw_Financials!K42 -> 0 | M42: Bunu akademik dille şöyle ifade etmelisin:
A43: Deferred Tax Assets | B43: =+final_results!B43-Raw_Financials!B43 -> 0 | C43: =+final_results!C43-Raw_Financials!C43 -> 0 | D43: =+final_results!D43-Raw_Financials!D43 -> 0 | E43: =+final_results!E43-Raw_Financials!E43 -> 0 | F43: =+final_results!F43-Raw_Financials!F43 -> 0 | G43: =+final_results!G43-Raw_Financials!G43 -> 0 | H43: =+final_results!H43-Raw_Financials!H43 -> 0 | I43: =+final_results!I43-Raw_Financials!I43 -> 0 | ... K43: =+final_results!K43-Raw_Financials!K43 -> 0
A44: Other Receivables(LTP) | B44: =+final_results!B44-Raw_Financials!B44 -> 0 | C44: =+final_results!C44-Raw_Financials!C44 -> 0 | D44: =+final_results!D44-Raw_Financials!D44 -> 0 | E44: =+final_results!E44-Raw_Financials!E44 -> 0 | F44: =+final_results!F44-Raw_Financials!F44 -> 0 | G44: =+final_results!G44-Raw_Financials!G44 -> 0 | H44: =+final_results!H44-Raw_Financials!H44 -> 0 | I44: =+final_results!I44-Raw_Financials!I44 -> 0 | ... K44: =+final_results!K44-Raw_Financials!K44 -> 0 | M44: "Veri setindeki aykırı değerlerin (outliers) tespiti aşamasında, Türkiye ekonomisindeki yüksek enflasyonist etkinin, nominal değerlerde yanıltıcı varyans (pseudo-variance) yaratmasını engellemek amacıyla 'Domain Transformation' yöntemi uygulanmıştır.
A45: Prepayments(LTP) | B45: =+final_results!B45-Raw_Financials!B45 -> 0 | C45: =+final_results!C45-Raw_Financials!C45 -> 0 | D45: =+final_results!D45-Raw_Financials!D45 -> 0 | E45: =+final_results!E45-Raw_Financials!E45 -> 0 | F45: =+final_results!F45-Raw_Financials!F45 -> 0 | G45: =+final_results!G45-Raw_Financials!G45 -> 0 | H45: =+final_results!H45-Raw_Financials!H45 -> 0 | I45: =+final_results!I45-Raw_Financials!I45 -> 0 | ... K45: =+final_results!K45-Raw_Financials!K45 -> 0
A46: Restricted Cash | B46: =+final_results!B46-Raw_Financials!B46 -> 0 | C46: =+final_results!C46-Raw_Financials!C46 -> 0 | D46: =+final_results!D46-Raw_Financials!D46 -> 0 | E46: =+final_results!E46-Raw_Financials!E46 -> 0 | F46: =+final_results!F46-Raw_Financials!F46 -> 0 | G46: =+final_results!G46-Raw_Financials!G46 -> 0 | H46: =+final_results!H46-Raw_Financials!H46 -> 0 | I46: =+final_results!I46-Raw_Financials!I46 -> 0 | ... K46: =+final_results!K46-Raw_Financials!K46 -> 0 | M46: Veriler günlük kur üzerinden USD'ye dönüştürülerek enflasyondan arındırılmış (detrended),
A47: Operating Lease Receivables | B47: =+final_results!B47-Raw_Financials!B47 -> 0 | C47: =+final_results!C47-Raw_Financials!C47 -> 0 | D47: =+final_results!D47-Raw_Financials!D47 -> 0 | E47: =+final_results!E47-Raw_Financials!E47 -> 0 | F47: =+final_results!F47-Raw_Financials!F47 -> 0 | G47: =+final_results!G47-Raw_Financials!G47 -> 0 | H47: =+final_results!H47-Raw_Financials!H47 -> 0 | I47: =+final_results!I47-Raw_Financials!I47 -> 0 | ... K47: =+final_results!K47-Raw_Financials!K47 -> 0
A48: Land (Current) | B48: =+final_results!B48-Raw_Financials!B48 -> 0 | C48: =+final_results!C48-Raw_Financials!C48 -> 0 | D48: =+final_results!D48-Raw_Financials!D48 -> 0 | E48: =+final_results!E48-Raw_Financials!E48 -> 0 | F48: =+final_results!F48-Raw_Financials!F48 -> 0 | G48: =+final_results!G48-Raw_Financials!G48 -> 0 | H48: =+final_results!H48-Raw_Financials!H48 -> 0 | I48: =+final_results!I48-Raw_Financials!I48 -> 0 | ... K48: =+final_results!K48-Raw_Financials!K48 -> 0 | M48: Bu reel değerler üzerinde 3-IQR Winsorization (sınırlama) uygulanmış,
A49: Developments in Progress | B49: =+final_results!B49-Raw_Financials!B49 -> 0 | C49: =+final_results!C49-Raw_Financials!C49 -> 0 | D49: =+final_results!D49-Raw_Financials!D49 -> 0 | E49: =+final_results!E49-Raw_Financials!E49 -> 0 | F49: =+final_results!F49-Raw_Financials!F49 -> 0 | G49: =+final_results!G49-Raw_Financials!G49 -> 0 | H49: =+final_results!H49-Raw_Financials!H49 -> 0 | I49: =+final_results!I49-Raw_Financials!I49 -> 0 | ... K49: =+final_results!K49-Raw_Financials!K49 -> 0
A50: Developments Finished | B50: =+final_results!B50-Raw_Financials!B50 -> 0 | C50: =+final_results!C50-Raw_Financials!C50 -> 0 | D50: =+final_results!D50-Raw_Financials!D50 -> 0 | E50: =+final_results!E50-Raw_Financials!E50 -> 0 | F50: =+final_results!F50-Raw_Financials!F50 -> 0 | G50: =+final_results!G50-Raw_Financials!G50 -> 0 | H50: =+final_results!H50-Raw_Financials!H50 -> 0 | I50: =+final_results!I50-Raw_Financials!I50 -> 0 | ... K50: =+final_results!K50-Raw_Financials!K50 -> 0 | M50: Temizlenen veriler tekrar ilgili tarihlerin kurları ile çarpılarak orijinal para birimine (TRY) geri döndürülmüştür.
A51: Inventories raw material | B51: =+final_results!B51-Raw_Financials!B51 -> 0 | C51: =+final_results!C51-Raw_Financials!C51 -> 0 | D51: =+final_results!D51-Raw_Financials!D51 -> 0 | E51: =+final_results!E51-Raw_Financials!E51 -> 0 | F51: =+final_results!F51-Raw_Financials!F51 -> 0 | G51: =+final_results!G51-Raw_Financials!G51 -> 0 | H51: =+final_results!H51-Raw_Financials!H51 -> 0 | I51: =+final_results!I51-Raw_Financials!I51 -> 0 | ... K51: =+final_results!K51-Raw_Financials!K51 -> 0
A52: Inventories not finished | B52: =+final_results!B52-Raw_Financials!B52 -> 0 | C52: =+final_results!C52-Raw_Financials!C52 -> 0 | D52: =+final_results!D52-Raw_Financials!D52 -> 0 | E52: =+final_results!E52-Raw_Financials!E52 -> 0 | F52: =+final_results!F52-Raw_Financials!F52 -> 0 | G52: =+final_results!G52-Raw_Financials!G52 -> 0 | H52: =+final_results!H52-Raw_Financials!H52 -> 0 | I52: =+final_results!I52-Raw_Financials!I52 -> 0 | ... K52: =+final_results!K52-Raw_Financials!K52 -> 0 | M52: Bu sayede enflasyonist trend korunmuş, ancak yapısal aykırı değerler temizlenmiştir."
A53: Inventories finished | B53: =+final_results!B53-Raw_Financials!B53 -> 0 | C53: =+final_results!C53-Raw_Financials!C53 -> 0 | D53: =+final_results!D53-Raw_Financials!D53 -> 0 | E53: =+final_results!E53-Raw_Financials!E53 -> 0 | F53: =+final_results!F53-Raw_Financials!F53 -> 0 | G53: =+final_results!G53-Raw_Financials!G53 -> 0 | H53: =+final_results!H53-Raw_Financials!H53 -> 0 | I53: =+final_results!I53-Raw_Financials!I53 -> 0 | ... K53: =+final_results!K53-Raw_Financials!K53 -> 0
A54: Depreciation Inventories(-) | B54: =+final_results!B54-Raw_Financials!B54 -> 0 | C54: =+final_results!C54-Raw_Financials!C54 -> 0 | D54: =+final_results!D54-Raw_Financials!D54 -> 0 | E54: =+final_results!E54-Raw_Financials!E54 -> 0 | F54: =+final_results!F54-Raw_Financials!F54 -> 0 | G54: =+final_results!G54-Raw_Financials!G54 -> 0 | H54: =+final_results!H54-Raw_Financials!H54 -> 0 | I54: =+final_results!I54-Raw_Financials!I54 -> 0 | ... K54: =+final_results!K54-Raw_Financials!K54 -> 0
A55: Prepayments suppliers | B55: =+final_results!B55-Raw_Financials!B55 -> 0 | C55: =+final_results!C55-Raw_Financials!C55 -> 0 | D55: =+final_results!D55-Raw_Financials!D55 -> 0 | E55: =+final_results!E55-Raw_Financials!E55 -> 0 | F55: =+final_results!F55-Raw_Financials!F55 -> 0 | G55: =+final_results!G55-Raw_Financials!G55 -> 0 | H55: =+final_results!H55-Raw_Financials!H55 -> 0 | I55: =+final_results!I55-Raw_Financials!I55 -> -16913.853 | ... K55: =+final_results!K55-Raw_Financials!K55 -> 0
A56: Total Inventories | B56: =+final_results!B56-Raw_Financials!B56 -> 0 | C56: =+final_results!C56-Raw_Financials!C56 -> 0 | D56: =+final_results!D56-Raw_Financials!D56 -> 0 | E56: =+final_results!E56-Raw_Financials!E56 -> 0 | F56: =+final_results!F56-Raw_Financials!F56 -> 0 | G56: =+final_results!G56-Raw_Financials!G56 -> 0 | H56: =+final_results!H56-Raw_Financials!H56 -> 0 | I56: =+final_results!I56-Raw_Financials!I56 -> 0 | ... K56: =+final_results!K56-Raw_Financials!K56 -> 0
A57: Due from JVs & Partnerships | B57: =+final_results!B57-Raw_Financials!B57 -> 0 | C57: =+final_results!C57-Raw_Financials!C57 -> 0 | D57: =+final_results!D57-Raw_Financials!D57 -> 0 | E57: =+final_results!E57-Raw_Financials!E57 -> 0 | F57: =+final_results!F57-Raw_Financials!F57 -> 0 | G57: =+final_results!G57-Raw_Financials!G57 -> 0 | H57: =+final_results!H57-Raw_Financials!H57 -> 0 | I57: =+final_results!I57-Raw_Financials!I57 -> 0 | ... K57: =+final_results!K57-Raw_Financials!K57 -> 0
A58: Due from Related Parties(CP) | B58: =+final_results!B58-Raw_Financials!B58 -> 0 | C58: =+final_results!C58-Raw_Financials!C58 -> 0 | D58: =+final_results!D58-Raw_Financials!D58 -> 0 | E58: =+final_results!E58-Raw_Financials!E58 -> 0 | F58: =+final_results!F58-Raw_Financials!F58 -> 0 | G58: =+final_results!G58-Raw_Financials!G58 -> 0 | H58: =+final_results!H58-Raw_Financials!H58 -> 0 | I58: =+final_results!I58-Raw_Financials!I58 -> -77608.136 | ... K58: =+final_results!K58-Raw_Financials!K58 -> 0
A59: Due from S'holder(CP) | B59: =+final_results!B59-Raw_Financials!B59 -> 0 | C59: =+final_results!C59-Raw_Financials!C59 -> 0 | D59: =+final_results!D59-Raw_Financials!D59 -> -1171.987 | E59: =+final_results!E59-Raw_Financials!E59 -> 0 | F59: =+final_results!F59-Raw_Financials!F59 -> 0 | G59: =+final_results!G59-Raw_Financials!G59 -> 0 | H59: =+final_results!H59-Raw_Financials!H59 -> 0 | I59: =+final_results!I59-Raw_Financials!I59 -> 0 | ... K59: =+final_results!K59-Raw_Financials!K59 -> 0
A60: Short Term Securities | B60: =+final_results!B60-Raw_Financials!B60 -> 0 | C60: =+final_results!C60-Raw_Financials!C60 -> 0 | D60: =+final_results!D60-Raw_Financials!D60 -> 0 | E60: =+final_results!E60-Raw_Financials!E60 -> 0 | F60: =+final_results!F60-Raw_Financials!F60 -> 0 | G60: =+final_results!G60-Raw_Financials!G60 -> 0 | H60: =+final_results!H60-Raw_Financials!H60 -> 0 | I60: =+final_results!I60-Raw_Financials!I60 -> 0 | ... K60: =+final_results!K60-Raw_Financials!K60 -> 0
A61: Secur & Other Fincl Assets(CP) | B61: =+final_results!B61-Raw_Financials!B61 -> 0 | C61: =+final_results!C61-Raw_Financials!C61 -> 0 | D61: =+final_results!D61-Raw_Financials!D61 -> 0 | E61: =+final_results!E61-Raw_Financials!E61 -> 0 | F61: =+final_results!F61-Raw_Financials!F61 -> 0 | G61: =+final_results!G61-Raw_Financials!G61 -> 0 | H61: =+final_results!H61-Raw_Financials!H61 -> 0 | I61: =+final_results!I61-Raw_Financials!I61 -> 0 | ... K61: =+final_results!K61-Raw_Financials!K61 -> 0
A62: Deriv & Hedg Assets(CP) | B62: =+final_results!B62-Raw_Financials!B62 -> 0 | C62: =+final_results!C62-Raw_Financials!C62 -> 0 | D62: =+final_results!D62-Raw_Financials!D62 -> 0 | E62: =+final_results!E62-Raw_Financials!E62 -> 0 | F62: =+final_results!F62-Raw_Financials!F62 -> 0 | G62: =+final_results!G62-Raw_Financials!G62 -> 0 | H62: =+final_results!H62-Raw_Financials!H62 -> 0 | I62: =+final_results!I62-Raw_Financials!I62 -> 0 | ... K62: =+final_results!K62-Raw_Financials!K62 -> 0
A63: Assets Plgd Under Securitization | B63: =+final_results!B63-Raw_Financials!B63 -> 0 | C63: =+final_results!C63-Raw_Financials!C63 -> 0 | D63: =+final_results!D63-Raw_Financials!D63 -> 0 | E63: =+final_results!E63-Raw_Financials!E63 -> 0 | F63: =+final_results!F63-Raw_Financials!F63 -> 0 | G63: =+final_results!G63-Raw_Financials!G63 -> 0 | H63: =+final_results!H63-Raw_Financials!H63 -> 0 | I63: =+final_results!I63-Raw_Financials!I63 -> 0 | ... K63: =+final_results!K63-Raw_Financials!K63 -> 0
A64: Current Tax Receivables | B64: =+final_results!B64-Raw_Financials!B64 -> -60591.212 | C64: =+final_results!C64-Raw_Financials!C64 -> 0 | D64: =+final_results!D64-Raw_Financials!D64 -> 0 | E64: =+final_results!E64-Raw_Financials!E64 -> 0 | F64: =+final_results!F64-Raw_Financials!F64 -> 0 | G64: =+final_results!G64-Raw_Financials!G64 -> 0 | H64: =+final_results!H64-Raw_Financials!H64 -> 0 | I64: =+final_results!I64-Raw_Financials!I64 -> 0 | ... K64: =+final_results!K64-Raw_Financials!K64 -> 0
... A225: Minority Interests | B225: =+final_results!B225-Raw_Financials!B225 -> 0 | C225: =+final_results!C225-Raw_Financials!C225 -> 0 | D225: =+final_results!D225-Raw_Financials!D225 -> 0 | E225: =+final_results!E225-Raw_Financials!E225 -> 0 | F225: =+final_results!F225-Raw_Financials!F225 -> 0 | G225: =+final_results!G225-Raw_Financials!G225 -> 0 | H225: =+final_results!H225-Raw_Financials!H225 -> 0 | I225: =+final_results!I225-Raw_Financials!I225 -> 0 | ... K225: =+final_results!K225-Raw_Financials!K225 -> 0

Sheet Macro_Monthly
A1: date | B1: usdtry | C1: eurtry | D1: tcmb_policy_rate | E1: hh_inflation_yoy | F1: Paste your columns directly into B–E. Dates are pre-filled (monthly).
A2: 42005 | B2: 2.3283429 | C2: 2.7162143 | D2: 7.75 | E2: 7.24
A3: 42036 | B3: 2.455225 | C3: 2.78988 | D3: 7.5 | E3: 7.55
A4: 42064 | B4: 2.5838409 | C4: 2.80465 | D4: 7.5 | E4: 7.61
A5: 42095 | B5: 2.6481429 | C5: 2.8534048 | D5: 7.5 | E5: 7.91
A6: 42125 | B6: 2.6461368 | C6: 2.9551105 | D6: 7.5 | E6: 8.09
A7: 42156 | B7: 2.7011591 | C7: 3.0267455 | D7: 7.5 | E7: 7.2
A8: 42186 | B8: 2.6946045 | C8: 2.9709818 | D8: 7.5 | E8: 6.81
A9: 42217 | B9: 2.8455571 | C9: 3.167219 | D9: 7.5 | E9: 7.14
A10: 42248 | B10: 3.002715 | C10: 3.3749 | D10: 7.5 | E10: 7.95
A11: 42278 | B11: 2.9295762 | C11: 3.2986048 | D11: 7.5 | E11: 7.58
A12: 42309 | B12: 2.8712857 | C12: 3.0894333 | D12: 7.5 | E12: 8.1
A13: 42339 | B13: 2.9172348 | C13: 3.1696913 | D13: 7.5 | E13: 8.81
... A121: 45627 | B121: 34.903823 | C121: 36.577014 | D121: 47.5 | E121: 44.38
